Workbook

Sheet studios
A1: _RowNum | B1: studio_ID | C1: studioname | D1: contact | E1: fname | F1: surname | G1: email | H1: mobile | I1: city | J1: countryID | K1: instagram | L1: pincode | M1: datecreated | N1: lastupdated | O1: ipaddress | P1: sessionID | Q1: secureno | R1: duplicates | S1: bulk_link | T1: bulk_uploaded | U1: filler
A2: 0 | B2: 2 | C2: ARISTO DANCE | E2: Luīza | F2: ŠEPEĻEVA | G2: luiza.sepeleva@gmail.com | H2: +371 27903343 | I2: M&#256;RUPE | J2: 119 | K2: dsaristo_lv | L2: 309809 | M2: 44956.391 | N2: 45793.84 | O2: 80.89.77.147 | P2: 183465237 | Q2: 309809183465237 | R2: ARISTO DANCE luiza.sepeleva@gmail.com309809 | T2: 0
A3: 1 | B3: 3 | C3: BAZA DANCE COMPANY | E3: Marija | F3: SMOLENKOVA | G3: maria.smolenkova95@gmail.com | H3: +371 26785285 | I3: RĪGA | J3: 119 | K3: @maria.smolenkova | L3: 414484 | M3: 44956.488 | N3: 45934.495 | O3: 83.99.244.52 | P3: 263239188 | Q3: 414484263239188 | R3: BAZA DANCE COMPANYmaria.smolenkova95@gmail.com414484 | S3: https://upcdn.io/W23MT4R/raw/uploads/2025/10/04/4jTomEFp6d-MADNESS%20TEAM.docx | T3: 1
A4: 2 | B4: 4 | C4: ZFORCE | E4: Svetlana | F4: KOROLE | G4: lanakor@inbox.lv | H4: +371 29684055 | I4: RĪGA | J4: 119 | L4: 308129 | M4: 44956.518 | N4: 45216.341 | O4: 90.139.255.91 | P4: 868943437 | Q4: 308129868943437 | R4: ZFORCElanakor@inbox.lv308129 | T4: 0
A5: 3 | B5: 5 | C5: MUSTAMÄE HUVIKOOL ESTRAADITANTSUKOOL PEPPY DANCE | E5: Jekaterina | F5: ILNITSKAJA | G5: jekaterina.muravljova@gmail.com | H5: +372 53663366 | I5: TALLINN | J5: 69 | L5: 683174 | M5: 44960.312 | N5: 44970.456 | O5: 80.235.84.93 | P5: 239718100 | Q5: 683174239718100 | R5: MUSTAMÄE HUVIKOOL ESTRAADITANTSUKOOL PEPPY DANCEjekaterina.muravljova@gmail.com683174 | T5: 0
A6: 4 | B6: 6 | C6: TANSSIVA PORVOO | E6: Mia | F6: KOPONEN | G6: tanssivaporvoo@gmail.com | H6: +358 407313175 | I6: PORVOO | J6: 75 | K6: tanssivaporvoo | L6: 412239 | M6: 44960.461 | N6: 44960.651 | O6: 77.105.123.85 | P6: 614487791 | Q6: 412239614487791 | R6: TANSSIVA PORVOOtanssivaporvoo@gmail.com412239 | T6: 0
A7: 5 | B7: 7 | C7: 1ST CUT DANCE BASE | E7: Jenny | F7: WOLKANOWSKI | G7: j.wolkanowski@1stcut.de | H7: +49 17621209594 | I7: GIESSEN | J7: 82 | L7: 668049 | M7: 44961.436 | N7: 44961.436 | O7: 77.12.113.111 | P7: 425241107 | Q7: 668049425241107 | R7: 1ST CUT DANCE BASEj.wolkanowski@1stcut.de668049 | T7: 0
A8: 6 | B8: 8 | C8: CHOREOGRAPHY STUDIO INKARELIS | E8: Mindaugas | F8: PADAGAS | G8: padagasmindaugas@gmail.com | H8: +370 65481824 | I8: KLAIPEDA | J8: 125 | L8: 374121 | M8: 44961.758 | N8: 44977.917 | O8: 90.139.19.127 | P8: 871366362 | Q8: 374121871366362 | R8: CHOREOGRAPHY STUDIO INKARELISpadagasmindaugas@gmail.com374121 | T8: 0
A9: 7 | B9: 9 | C9: DE ARTE | E9: Tatjana | F9: ABROSIMOVA | G9: tatjana.abrosimova@inbox.lv | H9: +371 29546247 | I9: RĪGA | J9: 119 | L9: 350201 | M9: 44963.302 | N9: 44963.308 | O9: 87.110.144.140 | P9: 178790097 | Q9: 350201178790097 | R9: DE ARTEtatjana.abrosimova@inbox.lv350201 | T9: 0
A10: 8 | B10: 10 | C10: DREAM DANCE STUDIO | E10: Darja | F10: STOJANE | G10: dancestudiodream@gmail.com | H10: +371 26724214 | I10: RĪGA | J10: 119 | L10: 267242 | M10: 44963.496 | N10: 45684.375 | O10: 90.139.19.127 | P10: 827049846 | Q10: 267242827049846 | R10: DREAM DANCE STUDIOdancestudiodream@gmail.com267242 | T10: 0
A11: 9 | B11: 11 | C11: DANCE STUDIO STARMIX | E11: Megija | F11: UPESJOZUPA | G11: mupesjozupa@gmail.com | H11: +371 26279720 | I11: TALSI | J11: 119 | L11: 424390 | M11: 44963.745 | N11: 44963.748 | O11: 80.89.77.255 | P11: 127265063 | Q11: 424390127265063 | R11: DANCE STUDIO STARMIXmupesjozupa@gmail.com424390 | T11: 0
A12: 10 | B12: 12 | C12: VOU DANCE GROUP | E12: Elle | F12: AGAR | G12: elle.agar.001@gmail.com | H12: +372 56822312 | I12: MULGI VALD | J12: 69 | L12: 818245 | M12: 44963.786 | N12: 44980.327 | O12: 90.190.141.84 | P12: 843055957 | Q12: 818245843055957 | R12: VOU DANCE GROUPelle.agar.001@gmail.com818245 | T12: 0
A13: 11 | B13: 13 | C13: MS DANCE GROUP | E13: Maria | F13: SALIENKO-ZAHAROVA | G13: marija.salijenko@gmail.com | H13: 29594128 | I13: RĪGA | J13: 119 | L13: 140197 | M13: 44964.309 | N13: 45568.419 | O13: 212.142.115.164 | P13: 193643433 | Q13: 140197193643433 | R13: MS DANCE GROUPmarija.salijenko@gmail.com140197 | T13: 0
A14: 12 | B14: 14 | C14: TEIXMA DANCE | E14: Teiksma | F14: ZIEMELE | G14: teixma@teixma.lv | H14: +371 23071100 | I14: OGRE - LIELVĀRDE - IKŠĶILE | J14: 119 | L14: 642925 | M14: 44964.397 | N14: 45687.419 | O14: 62.85.33.124 | P14: 936493350 | Q14: 642925936493350 | R14: TEIXMA DANCEteixma@teixma.lv642925 | T14: 0
A15: 13 | B15: 15 | C15: HOREOGRĀFISKAIS ANSAMBLIS KOLORĪTS | E15: Jolanta | F15: ROSLOVA | G15: jolja24@inbox.lv | H15: +371 29120948 | I15: RĒZEKNE | J15: 119 | L15: 374401 | M15: 44964.483 | N15: 44970.354 | O15: 81.198.91.5 | P15: 206435845 | Q15: 374401206435845 | R15: HOREOGRĀFISKAIS ANSAMBLIS KOLORĪTSjolja24@inbox.lv374401 | T15: 0
A16: 14 | B16: 16 | C16: SMILTE | E16: Ramona | F16: VALIUTE-ZUKAUSKIENE | G16: smilte.dance@gmail.com | H16: +370 60966577 | I16: KLAIPEDA | J16: 125 | L16: 984595 | M16: 44964.495 | N16: 44990.852 | O16: 86.100.21.26 | P16: 278715968 | Q16: 984595278715968 | R16: SMILTEsmilte.dance@gmail.com984595 | T16: 0
A17: 15 | B17: 17 | C17: CIARA DANCE SCHOOL | E17: Carolin | F17: ARNOLD | G17: info@tantsukoolciara.ee | H17: +372 5257153 | I17: TARTU | J17: 69 | K17: ciaratantsukool | L17: 246429 | M17: 44964.823 | N17: 44981.789 | O17: 90.191.83.114 | P17: 843891425 | Q17: 246429843891425 | R17: CIARA DANCE SCHOOLinfo@tantsukoolciara.ee246429 | T17: 0
A18: 16 | B18: 18 | C18: DANCE STUDIO DIAMOND | E18: Tatjana | F18: ČILIKINA | G18: caliente85@inbox.lv | H18: +371 22324147 | I18: RĪGA | J18: 119 | L18: 332111 | M18: 44965.454 | N18: 45001.468 | O18: 90.139.19.127 | P18: 528154260 | Q18: 332111528154260 | R18: DANCE STUDIO DIAMONDcaliente85@inbox.lv332111 | T18: 0
A19: 17 | B19: 19 | C19: DEJU STUDIJA 27 | E19: Kristine | F19: OLEKSENKO | G19: dejustudija27@gmail.com | H19: +371 26025883 | I19: RĪGA | J19: 119 | L19: 270391 | M19: 44968.416 | N19: 45688.88 | O19: 77.219.9.159 | P19: 932102781 | Q19: 270391932102781 | R19: DEJU STUDIJA 27dejustudija27@gmail.com270391 | T19: 0
A20: 18 | B20: 20 | C20: TANSSILA DANCE SCHOOL | E20: Iiris | F20: SALMENMAA | G20: iiris.salmenmaa@tanssila.fi | H20: +358 415254116 | I20: HELSINKI | J20: 75 | K20: @tanssila | L20: 200464 | M20: 44968.671 | N20: 45001.736 | O20: 90.139.19.127 | P20: 778329227 | Q20: 200464778329227 | R20: TANSSILA DANCE SCHOOLiiris.salmenmaa@tanssila.fi200464 | T20: 0
A21: 19 | B21: 21 | C21: ONYX DANCE STUUDIO | E21: Julia | F21: RAKOVA | G21: Juliaonyx@mail.ru | H21: +372 53324950 | I21: TALLINN | J21: 69 | L21: 314019 | M21: 44968.814 | N21: 44968.814 | O21: 90.191.32.192 | P21: 376599044 | Q21: 314019376599044 | R21: ONYX DANCE STUUDIOJuliaonyx@mail.ru314019 | T21: 0
A22: 20 | B22: 22 | C22: HOUSE OF BERRIES | E22: Alina | F22: MATVEJEVA | G22: malinawaack@gmail.com | H22: +371 29831175 | I22: RĪGA | J22: 119 | L22: 517885 | M22: 44969.368 | N22: 45330.538 | O22: 77.38.221.235 | P22: 615983790 | Q22: 517885615983790 | R22: HOUSE OF BERRIESmalinawaack@gmail.com517885 | T22: 0
A23: 21 | B23: 23 | C23: DANCE ART STUDIO SUNRISE | E23: Karina | F23: STAVEJEVA | G23: karina.stafejeva@gmail.com | H23: +371 26059098 | I23: RĪGA | J23: 119 | L23: 358978 | M23: 44970.258 | N23: 45677.421 | O23: 77.219.8.56 | P23: 749591488 | Q23: 358978749591488 | R23: DANCE ART STUDIO SUNRISEkarina.stafejeva@gmail.com358978 | T23: 0
A24: 22 | B24: 24 | C24: DANCE GROUP NEPOSEDY / TANTSUANSAMBEL NEPOSEDÕ | E24: Liina | F24: BARANOVA | G24: neposedo@gmail.com | H24: +372 59045153 | I24: TALLINN | J24: 69 | L24: 800094 | M24: 44970.433 | N24: 45355.481 | O24: 46.39.145.170 | P24: 906899026 | Q24: 800094906899026 | R24: DANCE GROUP NEPOSEDY / TANTSUANSAMBEL NEPOSEDÕneposedo@gmail.com800094 | T24: 0
A25: 23 | B25: 25 | C25: DEJU STUDIJA DIAMOND GROUP | E25: Jekaterina | F25: VASI&#315;JEVA | G25: diamondgroup@inbox.lv | I25: RĪGA | J25: 119 | L25: 503690 | M25: 44970.893 | N25: 45758.606 | O25: 78.84.128.94 | P25: 181494207 | Q25: 503690181494207 | R25: DEJU STUDIJA DIAMOND GROUPdiamondgroup@inbox.lv503690 | T25: 0
A26: 24 | B26: 26 | C26: DEJU SKOLA “DZIRNAS” | E26: Līga | F26: KAVACE | G26: ligakavace@gmail.com | H26: +371 25134521 | I26: RĪGA | J26: 119 | L26: 534718 | M26: 44971.247 | N26: 44971.247 | O26: 90.139.19.127 | P26: 201430433 | Q26: 534718201430433 | R26: DEJU SKOLA “DZIRNAS”ligakavace@gmail.com534718 | T26: 0
A27: 25 | B27: 27 | C27: DIAMOND | E27: Viana | F27: BARK&#256;NE | G27: viktorijalicite228@gmail.com | I27: LIVĀNI | J27: 119 | L27: 865196 | M27: 44971.608 | N27: 45777.875 | O27: 77.219.1.30 | P27: 985080328 | Q27: 865196985080328 | R27: DIAMONDviktorijalicite228@gmail.com865196 | T27: 0
A28: 26 | B28: 28 | C28: STUDIJA KRISTĀLS | E28: Kristiāna | F28: VINCJUNA | G28: Dejustudija_kristals@inbox.lv | H28: +371 26290501 | I28: SMILTENE | J28: 119 | L28: 994747 | M28: 44972.405 | N28: 44972.405 | O28: 77.219.12.251 | P28: 882069254 | Q28: 994747882069254 | R28: STUDIJA KRISTĀLSDejustudija_kristals@inbox.lv994747 | T28: 0
A29: 27 | B29: 29 | C29: GOLTSMAN BALLET STUDIO | E29: Maria | F29: GOLTSMAN | G29: goltsmanstudio@gmail.com | H29: +372 5062345 | I29: TALLINN | J29: 69 | L29: 303063 | M29: 44972.398 | N29: 44972.457 | O29: 185.244.103.2 | P29: 434412572 | Q29: 303063434412572 | R29: GOLTSMAN BALLET STUDIOgoltsmanstudio@gmail.com303063 | T29: 0
A30: 28 | B30: 30 | C30: STUUDIO JOY | E30: Marina | F30: JERJOMINA | G30: stuudiojoy@gmail.com | H30: +372 5100838 | I30: VALGA / TALLINN | J30: 69 | L30: 350479 | M30: 44972.472 | N30: 44999.405 | O30: 62.63.152.13 | P30: 482695504 | Q30: 350479482695504 | R30: STUUDIO JOY stuudiojoy@gmail.com350479 | T30: 0
A31: 29 | B31: 31 | C31: DANCE GROUP NEXT | E31: Konstantin | F31: KOLESNIKOV | G31: stapdancer@gmail.com | H31: +371 29533395 | I31: RĪGA | J31: 119 | L31: 676118 | M31: 44972.519 | N31: 45693.493 | O31: 90.139.19.127 | P31: 788141270 | Q31: 676118788141270 | R31: DANCE GROUP NEXTstapdancer@gmail.com676118 | T31: 0
A32: 30 | B32: 32 | C32: PREMIUM DANCE STUDIO | E32: Elīna | F32: ALEKSANDROVA | G32: premiumds@inbox.lv | H32: +371 29550531 | I32: RĪGA | J32: 119 | L32: 700686 | M32: 44972.522 | N32: 45679.469 | O32: 90.139.19.127 | P32: 751730266 | Q32: 700686751730266 | R32: PREMIUM DANCE STUDIOpremiumds@inbox.lv700686 | T32: 0
A33: 31 | B33: 33 | C33: TDB DANCE STUDIO | D33: NATALIA | E33: Tereza | F33: DINULA | G33: dancestudiotdb@gmail.com | H33: +371 26362908 | I33: R&#298;GA | J33: 119 | L33: 130685 | M33: 44973.311 | N33: 45938.811 | O33: 213.175.126.8 | P33: 631427387 | Q33: 130685631427387 | R33: TDB DANCE STUDIOdancestudiotdb@gmail.com130685 | T33: 0
A34: 32 | B34: 34 | C34: FLASH DANCE STUDIO | E34: Marina | F34: UNGURE | G34: a.filistejeva@inbox.lv | H34: +371 25926114 | I34: R&#298;GA | J34: 119 | K34: flash.dancestudio | L34: 316407 | M34: 44973.403 | N34: 45939.778 | O34: 90.139.19.127 | P34: 685303811 | Q34: 316407685303811 | R34: FLASH DANCE STUDIOa.filistejeva@inbox.lv316407 | T34: 0
A35: 33 | B35: 35 | C35: DANCING CRYSTAL | E35: Tatjana | F35: ZAGORSKA-UDAĻCOVA | G35: tatjana0505@inbox.lv | H35: +371 22014412 | I35: PĻAVIŅAS | J35: 119 | L35: 372754 | M35: 44973.853 | N35: 44973.855 | O35: 78.84.231.104 | P35: 475005630 | Q35: 372754475005630 | R35: DANCING CRYSTALtatjana0505@inbox.lv372754 | T35: 0
A36: 34 | B36: 36 | C36: DA KARUSELIS, DS CAROUSELL | E36: Tamara | F36: EIFEROVA | G36: tamara.eiferova@gmail.com | H36: +371 29491491 | I36: SALASPILS | J36: 119 | L36: 121662 | M36: 44974.352 | N36: 45350.382 | O36: 87.110.33.86 | P36: 654349494 | Q36: 121662654349494 | R36: DA KARUSELIS, DS CAROUSELLtamara.eiferova@gmail.com121662 | T36: 0
A37: 35 | B37: 37 | C37: DANCE STUDIO CIPRESE | E37: Patrīcija | F37: DANILEIKO | G37: patricijapetrovska@gmail.com | H37: +371 29921147 | I37: RĪGA | J37: 119 | L37: 609425 | M37: 44977.346 | N37: 45362.531 | O37: 77.38.166.178 | P37: 604190403 | Q37: 609425604190403 | R37: DANCE STUDIO CIPRESEpatricijapetrovska@gmail.com609425 | T37: 0
A38: 36 | B38: 38 | C38: RITMS | E38: Elina | F38: GAITJUKEVICA | G38: ritms@ritms.lv | H38: +371 29592133 | I38: RĪGA | J38: 119 | L38: 786449 | M38: 44977.782 | N38: 45371.464 | O38: 80.89.74.250 | P38: 513992270 | Q38: 786449513992270 | R38: RITMSritms@ritms.lv786449 | T38: 0
A39: 37 | B39: 39 | C39: FREAK DANCE | E39: Sofija anna | F39: ZADOROŽNAJA | G39: freakxxxdance@gmail.com | H39: +371 26682346 | I39: RĪGA | J39: 119 | K39: freak.x.dance | L39: 984448 | M39: 44978.582 | N39: 44978.595 | O39: 81.198.169.234 | P39: 535565465 | Q39: 984448535565465 | R39: FREAK DANCEfreakxxxdance@gmail.com984448 | T39: 0
A40: 38 | B40: 40 | C40: X-GENERATION | E40: Jelena | F40: KOVALENKO | G40: jelena.kovalenko75@gmail.com | H40: +372 5577759 | I40: TALLINN | J40: 69 | L40: 823405 | M40: 44978.624 | N40: 45688.813 | O40: 91.129.103.199 | P40: 476610299 | Q40: 823405476610299 | R40: X-GENERATIONjelena.kovalenko75@gmail.com823405 | T40: 0
A41: 39 | B41: 41 | C41: VS DANCE STUDIO | E41: Vera | F41: SERKEVIČA | G41: verastudio@inbox.lv | H41: +371 26729857 | I41: JURMALA | J41: 119 | L41: 705070 | M41: 44979.349 | N41: 45785.735 | P41: 183054789 | Q41: 705070183054789 | R41: VS DANCE STUDIOverastudio@inbox.lv705070 | T41: 0
A42: 40 | B42: 42 | C42: DANCE STUDIO ENERGY | E42: Natalija | F42: PAVLIKOVA | G42: miksy@mail.ru | H42: +370 62237822 | I42: VASAGINAS | J42: 125 | L42: 662754 | M42: 44979.731 | N42: 44979.731 | O42: 77.219.12.123 | P42: 389692244 | Q42: 662754389692244 | R42: DANCE STUDIO ENERGY miksy@mail.ru662754 | T42: 0
A43: 41 | B43: 43 | C43: "ŽVILGIS" | E43: Lina | F43: LINKĖ | G43: lina.linke@vydunas.lt | H43: +370 67676231 | I43: ŠILUTĖ | J43: 125 | K43: sokiu_kolektyvas_zvilgis | L43: 850619 | M43: 44979.75 | N43: 44979.771 | O43: 83.176.212.136 | P43: 694978214 | Q43: 850619694978214 | R43: "ŽVILGIS"lina.linke@vydunas.lt850619 | T43: 0
A44: 42 | B44: 44 | C44: STUDIO “SPACE” | E44: Elza | F44: FUNTA | G44: elizakaija@yahoo.co.uk | H44: +371 28687768 | I44: RĪGA | J44: 119 | K44: studiospacelv | L44: 546362 | M44: 44984.487 | N44: 45353.405 | O44: 213.205.240.67 | P44: 397882798 | Q44: 546362397882798 | R44: STUDIO “SPACE”elizakaija@yahoo.co.uk546362 | T44: 0
A45: 43 | B45: 45 | C45: DANCE THEATER "POLLY" | E45: Polina | F45: ZHUKOVA | G45: info@tantsuteaterpolly.ee | H45: +372 58452328 | I45: TALLINN | J45: 69 | L45: 220489 | M45: 44984.869 | N45: 44984.869 | O45: 90.139.155.100 | P45: 592996027 | Q45: 220489592996027 | R45: DANCE THEATER "POLLY"info@tantsuteaterpolly.ee220489 | T45: 0
A46: 44 | B46: 46 | C46: DANCE STUDIO "VILNIS" | E46: Vaida | F46: TAUKLIENE | G46: vaidance@yahoo.com | H46: +370 60064532 | I46: KĖDAINIAI | J46: 125 | L46: 923819 | M46: 44997.852 | N46: 44997.852 | O46: 94.244.112.6 | P46: 344590920 | Q46: 923819344590920 | R46: DANCE STUDIO "VILNIS"vaidance@yahoo.com923819 | T46: 0
A47: 45 | B47: 47 | C47: ATTITUDE HELSINKI | E47: Kasperi | F47: KOLEHMAINEN | G47: kasperi@attitudehelsinki.com | H47: +358 409673177 | I47: HELSINKI | J47: 75 | L47: 334455 | M47: 45266.377 | N47: 45266.377 | O47: 212.90.95.155 | P47: 834844787 | Q47: 334455834844787 | R47: ATTITUDE HELSINKIkasperi@attitudehelsinki.com334455 | T47: 0
A48: 46 | B48: 48 | C48: OLAM RIKUD | E48: Anastasija | F48: VOLODINA | G48: bachilovan@gmail.com | H48: +371 25259565 | I48: RĪGA | J48: 119 | L48: 123456 | M48: 45273.376 | N48: 45273.376 | O48: 85.254.223.73 | P48: 732423225 | Q48: 123456732423225 | R48: OLAM RIKUDbachilovan@gmail.com123456 | T48: 0
A49: 47 | B49: 49 | C49: INDANCE TALENT CENTER | E49: Alina | F49: KOWALSKI | G49: in.dance@yahoo.com | H49: +49 176 32690227 | I49: DORTMUND | J49: 82 | K49: indance | L49: 227227 | M49: 45295.504 | N49: 45563.511 | O49: 77.219.2.96 | P49: 753320537 | Q49: 227227753320537 | R49: INDANCE TALENT CENTERin.dance@yahoo.com227227 | T49: 0
A50: 48 | B50: 50 | C50: AGNETA DANCESCHOOL | E50: Agnes | F50: MÄGISMAA | G50: agnes.magismaa@gmail.com | H50: +372 58087606 | I50: TALLINN | J50: 69 | L50: 201983 | M50: 45297.229 | N50: 45338.377 | O50: 91.129.105.77 | P50: 951513478 | Q50: 201983951513478 | R50: AGNETA DANCESCHOOLagnes.magismaa@gmail.com201983 | T50: 0
A51: 49 | B51: 51 | C51: DANCE STUDIO INSPIRATION | E51: Olesja | F51: SKOROBOGATOVA | G51: lesskee29@gmail.com | H51: +372 56993463 | I51: NARVA | J51: 69 | L51: 922284 | M51: 45298.626 | N51: 45665.492 | O51: 87.119.182.189 | P51: 384695332 | Q51: 922284384695332 | R51: DANCE STUDIO INSPIRATIONlesskee29@gmail.com922284 | T51: 0
A52: 50 | B52: 52 | C52: IMPERIA DANCE & FITNESS STUDIO | E52: Anna | F52: KORBOZEROVA | G52: anna.korbozerova@gmail.com | H52: +358 451729693 | I52: HELSINKI | J52: 75 | L52: 220992 | M52: 45301.554 | N52: 45301.554 | O52: 88.114.17.193 | P52: 855804695 | Q52: 220992855804695 | R52: IMPERIA DANCE & FITNESS STUDIOanna.korbozerova@gmail.com220992 | T52: 0
A53: 51 | B53: 53 | C53: DEJU STUDIJA "BURAS"" | E53: Edīte | F53: ĀBELTIŅA | G53: edite.buras@gmail.com | H53: +371 26599335 | I53: SALASPILS | J53: 119 | L53: 196807 | M53: 45303.396 | N53: 45370.474 | O53: 80.89.72.12 | P53: 899027790 | Q53: 196807899027790 | R53: DEJU STUDIJA "BURAS""edite.buras@gmail.com196807 | T53: 0
A54: 52 | B54: 54 | C54: HOREOGRĀFISKAIS ANSAMBLIS "PĒRLĪTE" | E54: Marina | F54: DUMBERGA-LOBANOVA | G54: marina.dumberg@inbox.lv | H54: +371 20471745 | I54: RĪGA | J54: 119 | L54: 123456 | M54: 45303.716 | N54: 45683.756 | O54: 212.142.122.213 | P54: 873103315 | Q54: 123456873103315 | R54: HOREOGRĀFISKAIS ANSAMBLIS "PĒRLĪTE"marina.dumberg@inbox.lv123456 | T54: 0
A55: 53 | B55: 55 | C55: TANZTHEATER GRAZIA | E55: Kristina | F55: KLEIN | G55: kleinkristinahamburg@gmail.com | H55: +49 17627688009 | I55: HAMBURG | J55: 82 | L55: 998765 | M55: 45311.684 | N55: 45311.684 | O55: 46.114.174.26 | P55: 489828620 | Q55: 998765489828620 | R55: TANZTHEATER GRAZIA kleinkristinahamburg@gmail.com998765 | T55: 0
A56: 54 | B56: 56 | C56: MARIANNA BORZEMSKA | E56: Marianna | F56: BORZEMSKA | G56: wolf.mariannaru@gmail.com | H56: +371 24915511 | I56: RĪGA | J56: 119 | L56: 450918 | M56: 45312.704 | N56: 45312.704 | O56: 84.237.202.170 | P56: 977636029 | Q56: 450918977636029 | R56: MARIANNA BORZEMSKAwolf.mariannaru@gmail.com450918 | T56: 0
A57: 55 | B57: 57 | C57: SHOW DANCE MILAGRO | E57: Tatjana | F57: ZAKIROVA | G57: milagro2007@inbox.lv | H57: +371 29853179 | I57: RĪGA | J57: 119 | L57: 161708 | M57: 45312.749 | N57: 45312.749 | O57: 89.191.98.235 | P57: 751956876 | Q57: 161708751956876 | R57: SHOW DANCE MILAGROmilagro2007@inbox.lv161708 | T57: 0
A58: 56 | B58: 58 | C58: ROYAL DANCE STUDIO | E58: Justīne | F58: BALMANE | G58: justinebalmane@gmail.com | H58: +371 22465909 | I58: RĪGA | J58: 119 | L58: 422542 | M58: 45316.802 | N58: 45353.377 | O58: 77.93.6.99 | P58: 425228406 | Q58: 422542425228406 | R58: ROYAL DANCE STUDIOjustinebalmane@gmail.com422542 | T58: 0
A59: 57 | B59: 59 | C59: DEJU STUDIJA VIRZIENS | E59: Baiba | F59: APENA | G59: dejustudijavirziens@gmail.com | H59: +371 22017951 | I59: JŪRMALA | J59: 119 | K59: dejustudijavirziens | L59: 556677 | M59: 45317.356 | N59: 45330.335 | O59: 77.219.1.113 | P59: 837514326 | Q59: 556677837514326 | R59: DEJU STUDIJA VIRZIENSdejustudijavirziens@gmail.com556677 | T59: 0
A60: 58 | B60: 60 | C60: DEJU GRUPA HOPĀ | E60: Sanita | F60: OVČIČČIKOVA | G60: sanita.ovcinnikova@gmail.com | H60: +371 26626681 | I60: RĪGA | J60: 119 | L60: 202020 | M60: 45318.727 | N60: 45691.859 | O60: 77.219.7.148 | P60: 849365335 | Q60: 202020849365335 | R60: DEJU GRUPA HOPĀsanita.ovcinnikova@gmail.com202020 | T60: 0
A61: 59 | B61: 61 | C61: TANTSUKOLLEKTIIV ZAGADKA | E61: Natalja | F61: ABRAMOVA | G61: tkzagadka@gmail.com | H61: +372 58519368 | I61: KOHTLA-JÄRVE | J61: 69 | L61: 523397 | M61: 45322.877 | N61: 45629.365 | O61: 193.40.56.36 | P61: 180191433 | Q61: 523397180191433 | R61: TANTSUKOLLEKTIIV ZAGADKAtkzagadka@gmail.com523397 | T61: 0
A62: 60 | B62: 62 | C62: DANCE STUDIO ELFAS | E62: Eva | F62: FRICBERGA | G62: evaelfa@gmail.com | H62: +371 26241447 | I62: RĪGA TALSI ROJA | J62: 119 | L62: 353535 | M62: 45323.414 | N62: 45323.414 | O62: 77.219.12.187 | P62: 278720664 | Q62: 353535278720664 | R62: DANCE STUDIO ELFASevaelfa@gmail.com353535 | T62: 0
A63: 61 | B63: 63 | C63: STEP ON HOUSE OF DANCE | E63: Agne | F63: STEPONKEVICIUTE | G63: stepon.judesionamai@gmail.com | H63: +370 65485327 | I63: VILNIUS | J63: 125 | L63: 911322 | M63: 45323.439 | N63: 45713.044 | O63: 78.158.27.20 | P63: 493544749 | Q63: 911322493544749 | R63: STEP ON HOUSE OF DANCEstepon.judesionamai@gmail.com911322 | T63: 0
A64: 62 | B64: 64 | C64: STUDIO DANCE DREAM | E64: Rita | F64: AUSTRIN | G64: stuudiodancedream@gmail.com | H64: +372 56233288 | I64: VILJANDI | J64: 69 | L64: 140582 | M64: 45323.664 | N64: 45323.664 | O64: 90.133.206.20 | P64: 727222188 | Q64: 140582727222188 | R64: STUDIO DANCE DREAMstuudiodancedream@gmail.com140582 | T64: 0
A65: 63 | B65: 65 | C65: DANCE STUDIO "SANIVI" | E65: Sanita | F65: MARTI&#325;ENKO | G65: chytax@inbox.lv | H65: +371 25157512 | I65: AIZKRAUKLE / KOKNESE | J65: 119 | L65: 105205 | M65: 45324.298 | N65: 45714.033 | O65: 77.219.9.153 | P65: 976150162 | Q65: 105205976150162 | R65: DANCE STUDIO "SANIVI"chytax@inbox.lv105205 | T65: 0
A66: 64 | B66: 66 | C66: ERROR TANTSUKOOL | E66: Marju | F66: ASAROV | G66: errorstuudio@errorstuudio.ee | H66: +372 5133929 | I66: TARTU | J66: 69 | L66: 108202 | M66: 45324.517 | N66: 45324.554 | O66: 90.191.105.96 | P66: 698319875 | Q66: 108202698319875 | R66: ERROR TANTSUKOOLerrorstuudio@errorstuudio.ee108202 | T66: 0
A67: 65 | B67: 67 | C67: CIRKA STUDIJA "MELANŽ" | E67: Irina | F67: LEVIT | G67: cirka_studija_melanz@inbox.lv | H67: +371 29932786 | I67: RĪGA | J67: 119 | L67: 267111 | M67: 45328.391 | N67: 45332.404 | O67: 136.169.37.120 | P67: 523598096 | Q67: 267111523598096 | R67: CIRKA STUDIJA "MELANŽ"cirka_studija_melanz@inbox.lv267111 | T67: 0
A68: 66 | B68: 68 | C68: J-AR DANCE STUDIO | E68: Jevgenija | F68: KLAPERE | G68: balletdancer@inbox.lv | H68: +371 25927833 | I68: RIGA | J68: 119 | L68: 259278 | M68: 45329.493 | N68: 45329.493 | O68: 87.110.29.152 | P68: 811961900 | Q68: 259278811961900 | R68: J-AR DANCE STUDIOballetdancer@inbox.lv259278 | T68: 0
A69: 67 | B69: 69 | C69: DEJU SKOLA "VENDIJA" | E69: Arina | F69: DANCE SCHOOL VENDIA | G69: arina.bubovicha@gmail.com | H69: +371 26616872 | I69: RĪGA | J69: 119 | L69: 777744 | M69: 45330.525 | N69: 45330.525 | O69: 77.219.1.57 | P69: 710975152 | Q69: 777744710975152 | R69: DEJU SKOLA "VENDIJA"arina.bubovicha@gmail.com777744 | T69: 0
A70: 68 | B70: 70 | C70: SHOW GROUP "MIX" | E70: Jūlija | F70: LATSONE | G70: jlatsone@gmail.com | H70: +371 29164191 | I70: RĪGA | J70: 119 | L70: 214085 | M70: 45332.418 | N70: 45332.418 | P70: 129621113 | Q70: 214085129621113 | R70: SHOW GROUP "MIX"jlatsone@gmail.com214085 | T70: 0
A71: 69 | B71: 71 | C71: XENYDANCE STUDIO | E71: Ksenija | F71: Briede | G71: ksenija.briede@gmail.com | H71: +371 25968067 | I71: JĒKABPILS | J71: 119 | L71: 105205 | M71: 45332.418 | N71: 45332.418 | P71: 162860031 | Q71: 105205162860031 | R71: XENYDANCE STUDIOksenija.briede@gmail.com105205 | T71: 0
A72: 70 | B72: 72 | C72: DANCE STUDIO "BASSE" | E72: Vaida | F72: TAUKLIENE | G72: studijabasse@gmail.com | H72: +370 60064532 | I72: KAUNAS | J72: 125 | L72: 505605 | M72: 45340 | N72: 45340 | P72: 702830016 | Q72: 505605702830016 | R72: DANCE STUDIO "BASSE"studijabasse@gmail.com505605 | T72: 0
A73: 71 | B73: 73 | C73: DANCE STUDIO SONRISA | E73: Svetlana | F73: HUDABAŠJANA | G73: svetlana.kurnosova1228@gmail.com | H73: +371 28704865 | I73: RĪGA | J73: 119 | L73: 280294 | M73: 45352 | N73: 45685.746 | P73: 572647494 | Q73: 280294572647494 | R73: DANCE STUDIO SONRISAsvetlana.kurnosova1228@gmail.com280294 | T73: 0
A74: 72 | B74: 74 | C74: DANCE SCHOOL DREAMTEAM | E74: El&#299;na | F74: Freiberga | G74: dreamteam.dance.lv@gmail.com | H74: 26394221 | I74: RĪGA | J74: 119 | L74: 193193 | M74: 45363 | N74: 45719.557 | P74: 912488727 | Q74: 193193912488727 | R74: DANCE SCHOOL DREAMTEAMdreamteam.dance.lv@gmail.com193193 | T74: 0
A75: 73 | B75: 75 | C75: 105 DANCE COMPLEX | D75: MIRKA LILJEQVIST | E75: Mirka | F75: LILJEQVIST | G75: mirkaliljeqvist@gmail.com | H75: +358453177012 | I75: KOTKA | J75: 75 | L75: 105202 | M75: 45567.254 | N75: 45567.335 | O75: 85.76.79.17 | P75: 654408891 | Q75: 105202654408891 | R75: 105 DANCE COMPLEX mirkaliljeqvist@gmail.com105202 | T75: 0
A76: 74 | B76: 76 | C76: KULLERKUPP | E76: Jevgenia | F76: SELETSKAJA | G76: e.seletskaja@gmail.com | H76: +37255916202 | I76: NARVA-JÕESUU | J76: 69 | L76: 200222 | M76: 45567.293 | N76: 45567.293 | O76: 91.129.98.197 | P76: 654409457 | Q76: 200222654409457 | R76: KULLERKUPP e.seletskaja@gmail.com200222 | T76: 0
A77: 75 | B77: 77 | C77: DANCE STUDIO TAVO FORTŪNA | E77: Dovydas | F77: SLIVKA | G77: dovydassliv13@gmail.com | H77: +37065995796 | I77: PANEVĖŽYS / LITHUANIA | J77: 125 | L77: 210213 | M77: 45570.724 | N77: 45570.724 | O77: 84.15.190.202 | P77: 195918275 | Q77: 210213195918275 | R77: DANCE STUDIO TAVO FORTŪNAdovydassliv13@gmail.com210213 | T77: 0
A78: 76 | B78: 78 | C78: DANCEZONE FINLAND | E78: La-orwan | F78: CHAIYADET | G78: dancezonefinland@gmail.com | H78: +358409307760 | I78: KERAVA | J78: 75 | L78: 123456 | M78: 45572.703 | N78: 45572.703 | O78: 85.76.75.244 | P78: 543603464 | Q78: 123456543603464 | R78: DANCEZONE FINLAND dancezonefinland@gmail.com123456 | T78: 0
A79: 77 | B79: 79 | C79: TANTSUKOLLEKTIIV ANTREE | E79: Nadezda | F79: SLYUSARENKO | G79: nadezda.slyusarenko@mail.ru | H79: 37255682328 | I79: SILLAMÄE | J79: 69 | L79: 682328 | M79: 45574.634 | N79: 45574.634 | O79: 90.133.90.12 | P79: 887150209 | Q79: 682328887150209 | R79: TANTSUKOLLEKTIIV ANTREEnadezda.slyusarenko@mail.ru682328 | T79: 0
A80: 78 | B80: 80 | C80: MIX STUDIO | E80: Cecile | F80: ATAEI | G80: mixstudio.fi@hotmail.com | H80: +358504059953 | I80: MIKKELI | J80: 75 | L80: 832008 | M80: 45575.447 | N80: 45727.687 | O80: 80.89.77.61 | P80: 1030493574 | Q80: 8.320081e+15 | R80: MIX STUDIOmixstudio.fi@hotmail.com832008 | T80: 0
A81: 79 | B81: 81 | C81: GHETTO DANCE ACADEMY | E81: Elina | F81: LEVCENKO-GLADINA | G81: ravepeppka@gmail.com | H81: 28872105 | I81: RIGA | J81: 119 | L81: 230901 | M81: 45581.546 | N81: 45581.546 | O81: 83.99.144.4 | P81: 1037057711 | Q81: 2.309011e+15 | R81: GHETTO DANCE ACADEMYravepeppka@gmail.com230901 | T81: 0
A82: 80 | B82: 82 | C82: MELODY | E82: Ginta | F82: UPENIECE | G82: gintaupeniece@gmail.com | H82: 22042081 | I82: IECAVA | J82: 119 | L82: 123456 | M82: 45583.715 | N82: 45583.715 | O82: 81.198.190.181 | P82: 344969871 | Q82: 123456344969871 | R82: MELODYgintaupeniece@gmail.com123456 | T82: 0
A83: 81 | B83: 83 | C83: M-ART DANCE STUDIO | E83: Marta | F83: ANČEREVIČA | G83: martaancerevica@inbox.lv | H83: +37120403450 | I83: JURMALA | J83: 119 | L83: 333333 | M83: 45607.451 | N83: 45607.451 | O83: 212.3.198.161 | P83: 251916938 | Q83: 333333251916938 | R83: M-ART DANCE STUDIOmartaancerevica@inbox.lv333333 | T83: 0
A84: 82 | B84: 84 | C84: LA FEMME | E84: Laura | F84: STŪRAINE | G84: theroselaura@gmail.com | H84: 22033749 | I84: RIGA | J84: 119 | L84: 110302 | M84: 45608.348 | N84: 45608.348 | O84: 85.254.75.216 | P84: 410483839 | Q84: 110302410483839 | R84: LA FEMMEtheroselaura@gmail.com110302 | T84: 0
A85: 83 | B85: 85 | C85: LIFEDANCE STUUDIO | E85: Liis | F85: SARI | G85: liis@lifedance.ee | H85: 0037256983358 | I85: TALLINN | J85: 69 | L85: 120190 | M85: 45610.323 | N85: 45610.323 | O85: 91.129.96.174 | P85: 760436990 | Q85: 120190760436990 | R85: LIFEDANCE STUUDIOliis@lifedance.ee120190 | T85: 0
A86: 84 | B86: 86 | C86: BLOOM DANCE COMPANY | E86: Giada | F86: LUCIANI | G86: giada.luciani1995@gmail.com | H86: +46 733998124 | I86: MALMÖ | J86: 213 | L86: 260305 | M86: 45613.932 | N86: 45615.52 | O86: 194.34.233.19 | P86: 310730867 | Q86: 260305310730867 | R86: BLOOM DANCE COMPANYgiada.luciani1995@gmail.com260305 | T86: 0
A87: 85 | B87: 87 | C87: LEMONO DANCE CENTER | E87: Agnieszka czubak | F87: LEMONO DANCE CENTER | G87: kontakt@lemonodance.pl | H87: +48515175200 | I87: WARSZAWA | J87: 175 | L87: 121212 | M87: 45623.488 | N87: 45712.88 | O87: 94.240.0.1 | P87: 940243540 | Q87: 121212940243540 | R87: LEMONO DANCE CENTERkontakt@lemonodance.pl121212 | T87: 0
... A175: 173 | B175: 176 | C175: KLEBER DANCE STUDIO | E175: Silvia | F175: KONDRATIVA | G175: silviakondrat@gmail.com | H175: 26589635 | I175: VILNIUS | J175: 125 | L175: 123456 | M175: 45785.818 | N175: 45785.818 | O175: 212.3.198.115 | P175: 652325574 | Q175: 123456652325574 | R175: KLEBER DANCE STUDIOsilviakondrat@gmail.com123456 | T175: 0
A176: 174 | B176: 180 | C176: MARRAKECH DANCERS | D176: SIMON FENNELL | E176: Simon | F176: FENNELL | G176: safennell@btconnect.com | H176: +44 07507 853112 | I176: MARRAKECH | J176: 147 | K176: @saf_insta | L176: 222333 | M176: 45922.698 | N176: 45932.731 | O176: 162.158.122.3 | P176: 988765432 | Q176: 222333988765432 | R176: MARRAKECH DANCERS safennell@btconnect.com222333 | T176: 0
A177: 175 | B177: 181 | C177: BERLIN DANCE STUDIO | D177: ALEX PARIS | E177: Alex | F177: PARIS | G177: aleksparis2@gmail.com | H177: 37125511416 | I177: BERLIN | J177: 82 | L177: 555666 | M177: 45922.882 | N177: 45932.863 | O177: 104.23.199.38 | P177: 877987654 | Q177: 555666877987654 | R177: BERLIN DANCE STUDIOaleksparis2@gmail.com555666 | T177: 0
A178: 176 | B178: 182 | C178: ARTISTIQUE DANCE & PERFORM | D178: MY JOSEFSSON | G178: My@artistique.se | H178: +46765570754 | I178: GOTHENBURG | J178: 213 | K178: Artistique_goteborg | L178: 199107 | M178: 45935.83 | N178: 45946.52 | O178: 162.158.183.47 | P178: 766876543 | Q178: 199107766876543 | R178: ARTISTIQUE DANCE & PERFORMMy@artistique.se199107 | T178: 0
A179: 177 | B179: 184 | C179: PROJECT DANCE STUDIO | D179: 29644015 | G179: projectstudija@gmail.com | H179: 29644015 | I179: RIGA | J179: 119 | L179: 644015 | M179: 45938.496 | N179: 45938.496 | O179: 172.69.52.151 | P179: 655765432 | Q179: 644015655765432 | R179: PROJECT DANCE STUDIOprojectstudija@gmail.com644015 | T179: 0
A180: 178 | B180: 186 | C180: UNIQSY | D180: ALISE MOLE | G180: uniqsy.d@gmail.com | H180: +37127018794 | I180: DAUGAVPILS | J180: 119 | L180: 589132 | M180: 45938.892 | N180: 45938.892 | O180: 172.69.192.163 | P180: 892418886 | Q180: 589132892418886 | R180: UNIQSYuniqsy.d@gmail.com589132 | T180: 0
A181: 179 | B181: 187 | C181: MANIJA DANCE FAM | D181: MARI LUIZA MANIJA | G181: mariluizamanija@gmail.com | H181: +37120023155 | I181: RIGA | J181: 119 | L181: 223322 | M181: 45939.053 | N181: 45939.053 | O181: 172.69.192.164 | P181: 923324572 | Q181: 223322923324572 | R181: MANIJA DANCE FAMmariluizamanija@gmail.com223322 | T181: 0
A182: 180 | B182: 188 | C182: M&DANCE CREW | D182: MARI LUIZA MANIJA | G182: mariluizamanija@gmail.com | H182: +37120023155 | I182: RIGA | J182: 119 | L182: 221122 | M182: 45939.056 | N182: 45939.056 | O182: 172.69.192.164 | P182: 923324573 | Q182: 221122923324573 | R182: M&DANCE CREWmariluizamanija@gmail.com221122 | T182: 0
A183: 181 | B183: 190 | C183: GRESTUUDIO | D183: GRETE-L. GULBIS | G183: info@grestuudio.ee | H183: +37255553326 | I183: TALLINN | J183: 69 | L183: 110502 | M183: 45939.517 | N183: 45939.517 | O183: 172.69.136.201 | P183: 1001568786 | Q183: 1.105021e+15 | R183: GRESTUUDIOinfo@grestuudio.ee110502 | T183: 0
A184: 182 | B184: 191 | C184: LIFEDANCE STUUDIO | D184: LIIS SARI | G184: registreeri@lifedance.ee | H184: 0037256983358 | I184: TALLINN | J184: 69 | L184: 120190 | M184: 45939.573 | N184: 45939.573 | O184: 172.69.136.200 | P184: 1015470174 | Q184: 1.201901e+15 | R184: LIFEDANCE STUUDIOregistreeri@lifedance.ee120190 | T184: 0
A185: 183 | B185: 192 | C185: DANCEBOX STUDIO | D185: @DANCEBOX_FAMILY | G185: nata.sabartsina@gmail.com | H185: +37253477747 | I185: JÃ•HVI | J185: 69 | L185: 777321 | M185: 45939.613 | N185: 45939.613 | O185: 172.69.136.200 | P185: 1022104272 | Q185: 7.773211e+15 | R185: DANCEBOX STUDIOnata.sabartsina@gmail.com777321 | T185: 0
A186: 184 | B186: 193 | C186: GIFFORD DANCE ACADEMY | D186: REBECCA GIFFORD | G186: info@gifforddanceacademy.com | H186: 07585221513 | I186: SHEFFORD | J186: 235 | L186: 230595 | M186: 45939.643 | N186: 45981.02 | O186: 162.158.216.92 | P186: 1025219350 | Q186: 2.305951e+15 | R186: GIFFORD DANCE ACADEMYinfo@gifforddanceacademy.com230595 | S186: https://upcdn.io/W23MT4R/raw/uploads/2025/11/19/4jMgYrcmE9-Untitled%20spreadsheet.xlsx | T186: 1
A187: 185 | B187: 195 | C187: ELEVÃ‰ | D187: SAMANTA ZEIMULE | G187: balets.salaspils@gmail.com | H187: 27495735 | I187: SALASPILS | J187: 119 | L187: 211100 | M187: 45939.827 | N187: 45939.827 | O187: 172.69.192.163 | P187: 1059913018 | Q187: 2.1110011e+15 | R187: ELEVÃ‰balets.salaspils@gmail.com211100 | T187: 0
...

Sheet acts
A1: _RowNum | B1: act_ID | C1: eventID | D1: eventname | E1: studioID | F1: teamname | G1: actname | H1: act_format | I1: act_type | J1: comp_numbers | K1: act_nomination | L1: act_agegroup | M1: act_division | N1: act_min_age | O1: act_max_age | P1: mixedage | Q1: notes | R1: datecreated | S1: lastupdated | T1: duplicates | U1: filler
A2: 0 | B2: 6 | C2: 7 | D2: Riga | E2: 3 | F2: MADNESS TEAM | G2: ILLUSION | H2: group | K2: stage dance | L2: adult 18+ | R2: 45932.55 | S2: 45932.55 | T2: 3/7/MADNESS TEAM
A3: 1 | B3: 7 | C3: 7 | D3: Riga | E3: 3 | F3: MADNESS TEAM | G3: BUTTERFLY EFFECT | H3: group | K3: stage dance | L3: adult 18+ | R3: 45932.551 | S3: 45932.551 | T3: 3/7/MADNESS TEAM
A4: 2 | B4: 8 | C4: 7 | D4: Riga | E4: 3 | F4: MADNESS TEAM | G4: SYMBIOSIS | H4: group | K4: stage dance | L4: adult 18+ | R4: 45932.552 | S4: 45932.552 | T4: 3/7/MADNESS TEAM
A5: 3 | B5: 9 | C5: 9 | D5: World of Dance Latvia | E5: 3 | F5: MADNESS TEAM | G5: ILLUSION | H5: group | K5: stage dance | L5: over 18s | M5: Team | R5: 45932.553 | S5: 45932.553 | T5: 3/9/MADNESS TEAM
A6: 4 | B6: 10 | C6: 9 | D6: World of Dance Latvia | E6: 3 | F6: MADNESS TEAM | G6: BUTTERFLY EFFECT | H6: group | K6: stage dance | L6: over 18s | M6: Team | R6: 45932.554 | S6: 45932.554 | T6: 3/9/MADNESS TEAM
A7: 5 | B7: 11 | C7: 9 | D7: World of Dance Latvia | E7: 3 | F7: MADNESS TEAM | G7: SYMBIOSIS | H7: group | K7: stage dance | L7: over 18s | M7: Team | R7: 45932.554 | S7: 45932.554 | T7: 3/9/MADNESS TEAM
A8: 6 | B8: 12 | C8: 7 | D8: Riga | E8: 88 | F8: DANCEACT DANCE STUDIO | G8: 1 | H8: group | K8: contemp & modern | L8: 16-18 y | R8: 45939.378 | S8: 45939.378 | T8: 88/7/DANCEACT DANCE STUDIO
A9: 7 | B9: 13 | C9: 7 | D9: Riga | E9: 88 | F9: DANCEACT DANCE STUDIO | G9: 2 | H9: group | K9: stage dance | L9: 16-18 y | R9: 45939.379 | S9: 45939.379 | T9: 88/7/DANCEACT DANCE STUDIO
A10: 8 | B10: 14 | C10: 7 | D10: Riga | E10: 88 | F10: DANCEACT DANCE STUDIO | G10: 3 | H10: group | K10: stage dance | L10: adult 18+ | R10: 45939.379 | S10: 45939.379 | T10: 88/7/DANCEACT DANCE STUDIO
A11: 9 | B11: 15 | C11: 7 | D11: Riga | E11: 88 | F11: DANCEACT DANCE STUDIO | G11: 4 | H11: group | K11: stage dance | L11: 16-18 y | R11: 45939.379 | S11: 45939.379 | T11: 88/7/DANCEACT DANCE STUDIO
A12: 10 | B12: 16 | C12: 7 | D12: Riga | E12: 88 | F12: DANCEACT DANCE STUDIO | G12: 5 | H12: group | K12: folk style dance | L12: 16-18 y | R12: 45939.38 | S12: 45939.38 | T12: 88/7/DANCEACT DANCE STUDIO
A13: 11 | B13: 17 | C13: 7 | D13: Riga | E13: 191 | F13: CRYSTALS | G13: THIS IS US | H13: group | K13: contemp & modern | L13: 10-12 y | R13: 45939.581 | S13: 45939.581 | T13: 191/7/CRYSTALS
A14: 12 | B14: 18 | C14: 7 | D14: Riga | E14: 191 | F14: ROSE PETALS | G14: ORDINARY | H14: group | K14: contemp & modern | L14: 10-12 y | R14: 45939.583 | S14: 45939.583 | T14: 191/7/ROSE PETALS
A15: 13 | B15: 19 | C15: 7 | D15: Riga | E15: 191 | F15: MERMAIDS | G15: BRIGHT STARS | H15: group | K15: contemp & modern | L15: 7-9 y | R15: 45939.584 | S15: 45939.584 | T15: 191/7/MERMAIDS
A16: 14 | B16: 20 | C16: 7 | D16: Riga | E16: 191 | F16: HIP HOP MINIONS | G16: URBAN KIDZ | H16: group | K16: hip hop & urban | L16: 10-12 y | R16: 45939.584 | S16: 45939.584 | T16: 191/7/HIP HOP MINIONS
A17: 15 | B17: 21 | C17: 7 | D17: Riga | E17: 182 | F17: BLENDED CREW | G17: COLLECTIVE PULS | H17: group | K17: contemp & modern | L17: adult 18+ | R17: 45946.503 | S17: 45946.503 | T17: 182/7/BLENDED CREW
A18: 16 | B18: 22 | C18: 9 | D18: World of Dance Latvia | E18: 199 | F18: ALICE SOSNOVSKA | G18: YOU CAN'T OUTRUN A SHADOW | H18: solo | K18: stage dance | L18: over 18s | M18: Styles | R18: 45953.541 | S18: 45953.541 | T18: 199/9/ALICE SOSNOVSKA
A19: 17 | B19: 23 | C19: 9 | D19: World of Dance Latvia | E19: 200 | F19: ANNA DUDARCHYK | G19: - | H19: solo | K19: stage dance | L19: over 18s | M19: 0 | R19: 45956.87 | S19: 45956.87 | T19: 200/9/ANNA DUDARCHYK
A20: 18 | B20: 24 | C20: 7 | D20: Riga | E20: 88 | F20: DANCEACT DANCE STUDIO | G20: 1 | H20: group | K20: stage dance | L20: 13-15 y | R20: 45967.592 | S20: 45967.592 | T20: 88/7/DANCEACT DANCE STUDIO
A21: 19 | B21: 25 | C21: 7 | D21: Riga | E21: 88 | F21: DANCEACT DANCE STUDIO | G21: 7 | H21: group | K21: hip hop & urban | L21: 16-18 y | R21: 45967.602 | S21: 45967.602 | T21: 88/7/DANCEACT DANCE STUDIO
A22: 20 | B22: 26 | C22: 8 | D22: Turkey | E22: 199 | F22: ALICE SOSNOVSKA | G22: STRIKEOUT | H22: solo | K22: hip hop & urban | L22: adult 18+ | R22: 45971.909 | S22: 45971.909 | T22: 199/8/ALICE SOSNOVSKA
A23: 21 | B23: 27 | C23: 8 | D23: Turkey | E23: 193 | F23: GIFFORD DANCE ACADEMY | G23: TEARS OF AN ANGEL | H23: group | K23: contemp & jazz-modern | L23: 13-15 y | R23: 45981.61 | S23: 45981.61 | T23: 193/8/GIFFORD DANCE ACADEMY
A24: 22 | B24: 28 | C24: 7 | D24: Riga | E24: 186 | F24: UNIQSY | G24: UNIVERSE WARRIORS | H24: group | K24: stage dance | L24: 13-15 y | R24: 45982.03 | S24: 45982.03 | T24: 186/7/UNIQSY
A25: 23 | B25: 29 | C25: 8 | D25: Turkey | E25: 193 | F25: GIFFORD DANCE ACADEMY | G25: THE WINNER TAKES IT ALL | H25: group | K25: contemp & jazz-modern | L25: 13-15 y | R25: 45983.47 | S25: 45983.47 | T25: 193/8/GIFFORD DANCE ACADEMY
A26: 24 | B26: 30 | C26: 8 | D26: Turkey | E26: 193 | F26: GIFFORD DANCE ACADEMY | G26: AIN'T NO OTHER MAN | H26: group | K26: contemp & jazz-modern | L26: 13-15 y | R26: 45983.471 | S26: 45983.471 | T26: 193/8/GIFFORD DANCE ACADEMY
A27: 25 | B27: 31 | C27: 8 | D27: Turkey | E27: 193 | F27: GIFFORD DANCE ACADEMY | G27: TAKE IT ALL | H27: group | K27: contemp & jazz-modern | L27: 13-15 y | R27: 45983.472 | S27: 45983.472 | T27: 193/8/GIFFORD DANCE ACADEMY
A28: 26 | B28: 32 | C28: 8 | D28: Turkey | E28: 193 | F28: GIFFORD DANCE ACADEMY | G28: HEAVEN IS A PLACE ON EARTH | H28: solo | K28: contemp & jazz-modern | L28: 10-12 y | R28: 45985.749 | S28: 45985.749 | T28: 193/8/GIFFORD DANCE ACADEMY
A29: 27 | B29: 33 | C29: 8 | D29: Turkey | E29: 193 | F29: GIFFORD DANCE ACADEMY | G29: SWEET CHILD Oâ€™MINE | H29: solo | K29: contemp & jazz-modern | L29: 10-12 y | R29: 45985.75 | S29: 45985.75 | T29: 193/8/GIFFORD DANCE ACADEMY
A30: 28 | B30: 34 | C30: 8 | D30: Turkey | E30: 193 | F30: GIFFORD DANCE ACADEMY | G30: ALWAYS REMEMBER US THIS WAY | H30: duo | K30: contemp & jazz-modern | L30: 10-12 y | R30: 45985.751 | S30: 45985.751 | T30: 193/8/GIFFORD DANCE ACADEMY
A31: 29 | B31: 35 | C31: 8 | D31: Turkey | E31: 193 | F31: GIFFORD DANCE ACADEMY | G31: GOOD TO GO | H31: duo | K31: contemp & jazz-modern | L31: 13-15 y | R31: 45985.752 | S31: 45985.752 | T31: 193/8/GIFFORD DANCE ACADEMY
... A33: 31 | B33: 37 | C33: 8 | D33: Turkey | E33: 203 | F33: LADY ELASTIC | G33: PASSION | H33: solo | K33: contemp & jazz-modern | L33: adult 18+ | R33: 45985.923 | S33: 45985.923 | T33: 203/8/LADY ELASTIC
A34: 32 | B34: 38 | C34: 9 | D34: World of Dance Latvia | E34: 205 | F34: SUN+ MINIT | G34: GET UP! | H34: group | K34: hip hop & urban | L34: under 18s | M34: Junior | R34: 45992.552 | S34: 45992.552 | T34: 205/9/SUN+ MINIT

Sheet dancers
A1: _RowNum | B1: dancer_ID | C1: studioID | D1: dancer | E1: dateofbirth | F1: dd_dob | G1: mm_dob | H1: year_dob | I1: datecreated | J1: lastupdated | K1: duplicates | L1: filler
A2: 0 | B2: 1 | C2: 3 | D2: Marija Smiolenkova | E2: 34931 | F2: 20 | G2: 8 | H2: 1995 | I2: 45938.593 | J2: 45938.593 | K2: Marija Smiolenkova20/08/1995
A3: 1 | B3: 2 | C3: 3 | D3: ⁠Nataļja Dorošenko | E3: 35321 | F3: 13 | G3: 9 | H3: 1996 | I3: 45938.593 | J3: 45938.593 | K3: ⁠Nataļja Dorošenko13/09/1996
A4: 2 | B4: 3 | C4: 3 | D4: ⁠Viktorija Urbāne | E4: 36384 | F4: 12 | G4: 8 | H4: 1999 | I4: 45938.593 | J4: 45938.593 | K4: ⁠Viktorija Urbāne12/08/1999
A5: 3 | B5: 4 | C5: 3 | D5: Ksenija Sidorova | E5: 34541 | F5: 26 | G5: 7 | H5: 1994 | I5: 45938.593 | J5: 45938.593 | K5: Ksenija Sidorova26/07/1994
A6: 4 | B6: 5 | C6: 3 | D6: ⁠Darja Šiškina | E6: 35779 | F6: 15 | G6: 12 | H6: 1997 | I6: 45938.593 | J6: 45938.593 | K6: ⁠Darja Šiškina15/12/1997
A7: 5 | B7: 6 | C7: 3 | D7: Nikola Andrejeva | E7: 36071 | F7: 3 | G7: 10 | H7: 1998 | I7: 45938.593 | J7: 45938.593 | K7: Nikola Andrejeva03/10/1998
A8: 6 | B8: 7 | C8: 3 | D8: ⁠Alīna Demidova | E8: 32309 | F8: 15 | G8: 6 | H8: 1988 | I8: 45938.593 | J8: 45938.593 | K8: ⁠Alīna Demidova15/06/1988
A9: 7 | B9: 8 | C9: 3 | D9: ⁠Alina Černova | E9: 39643 | F9: 14 | G9: 7 | H9: 2008 | I9: 45938.593 | J9: 45938.593 | K9: ⁠Alina Černova14/07/2008
A10: 8 | B10: 9 | C10: 3 | D10: Jūlija Šveda | E10: 37608 | F10: 18 | G10: 12 | H10: 2002 | I10: 45938.593 | J10: 45938.593 | K10: Jūlija Šveda18/12/2002
A11: 9 | B11: 10 | C11: 3 | D11: ⁠Silvija Zaporožanu | E11: 33622 | F11: 19 | G11: 1 | H11: 1992 | I11: 45938.593 | J11: 45938.593 | K11: ⁠Silvija Zaporožanu19/01/1992
A12: 10 | B12: 11 | C12: 3 | D12: ⁠Ksenija Ulitova | E12: 38546 | F12: 13 | G12: 7 | H12: 2005 | I12: 45938.593 | J12: 45938.593 | K12: ⁠Ksenija Ulitova13/07/2005
A13: 11 | B13: 12 | C13: 3 | D13: Taisija Savina | E13: 38815 | F13: 8 | G13: 4 | H13: 2006 | I13: 45938.593 | J13: 45938.593 | K13: Taisija Savina08/04/2006
... A17: 15 | B17: 16 | C17: 3 | D17: ⁠Anna Aleksandra Romašenoka | E17: 37453 | F17: 16 | G17: 7 | H17: 2002 | I17: 45938.593 | J17: 45938.593 | K17: ⁠Anna Aleksandra Romašenoka16/07/2002

Sheet reserved_places
A1: _RowNum | B1: reserveID | C1: studioID | D1: event1 | E1: riga_acts | F1: riga_dancers | G1: riga_changed | H1: riga_datepaid | I1: riga_money | J1: event2 | K1: belek_acts | L1: belek_dancers | M1: belek_changed | N1: belek_datepaid | O1: belek_money | P1: event3 | Q1: wod_acts | R1: wod_dancers | S1: wod_changed | T1: wod_datepaid | U1: wod_money | V1: lastupdated | W1: eof | X1: block1
A2: 0 | B2: 1 | C2: 2 | D2: 7 | E2: 8 | F2: 79 | G2: 1 | H2: 367 | I2: 0 | J2: 8 | K2: 0 | L2: 0 | M2: 0 | N2: 367 | O2: 0 | P2: 9 | Q2: 2 | R2: 14 | S2: 1 | T2: 367 | U2: 0 | V2: 45932.941 | X2: 0 | Y2: =IFERROR(VLOOKUP(reserved_places[[#This Row],[studioID]],studios!$B:$C,2,FALSE),"") -> ARISTO DANCE
A3: 1 | B3: 2 | C3: 3 | D3: 7 | E3: 2 | F3: 16 | G3: 1 | H3: 367 | I3: 0 | J3: 8 | K3: 0 | L3: 0 | M3: 0 | N3: 367 | O3: 0 | P3: 9 | Q3: 3 | R3: 16 | S3: 1 | T3: 367 | U3: 0 | V3: 45954.581 | X3: 0 | Y3: =IFERROR(VLOOKUP(reserved_places[[#This Row],[studioID]],studios!$B:$C,2,FALSE),"") -> BAZA DANCE COMPANY
A4: 2 | B4: 3 | C4: 4 | D4: 7 | E4: 0 | F4: 0 | G4: 0 | H4: 367 | I4: 0 | J4: 8 | K4: 0 | L4: 0 | M4: 0 | N4: 367 | O4: 0 | P4: 9 | Q4: 0 | R4: 0 | S4: 0 | T4: 367 | U4: 0 | V4: 45929 | X4: 0 | Y4: =IFERROR(VLOOKUP(reserved_places[[#This Row],[studioID]],studios!$B:$C,2,FALSE),"") -> ZFORCE
A5: 3 | B5: 4 | C5: 5 | D5: 7 | E5: 0 | F5: 0 | G5: 0 | H5: 367 | I5: 0 | J5: 8 | K5: 0 | L5: 0 | M5: 0 | N5: 367 | O5: 0 | P5: 9 | Q5: 0 | R5: 0 | S5: 0 | T5: 367 | U5: 0 | V5: 45929 | X5: 0 | Y5: =IFERROR(VLOOKUP(reserved_places[[#This Row],[studioID]],studios!$B:$C,2,FALSE),"") -> MUSTAMÄE HUVIKOOL ESTRAADITANTSUKOOL PEPPY DANCE
A6: 4 | B6: 5 | C6: 6 | D6: 7 | E6: 0 | F6: 0 | G6: 0 | H6: 367 | I6: 0 | J6: 8 | K6: 0 | L6: 0 | M6: 0 | N6: 367 | O6: 0 | P6: 9 | Q6: 0 | R6: 0 | S6: 0 | T6: 367 | U6: 0 | V6: 45929 | X6: 0 | Y6: =IFERROR(VLOOKUP(reserved_places[[#This Row],[studioID]],studios!$B:$C,2,FALSE),"") -> TANSSIVA PORVOO
A7: 5 | B7: 6 | C7: 7 | D7: 7 | E7: 0 | F7: 0 | G7: 0 | H7: 367 | I7: 0 | J7: 8 | K7: 0 | L7: 0 | M7: 0 | N7: 367 | O7: 0 | P7: 9 | Q7: 0 | R7: 0 | S7: 0 | T7: 367 | U7: 0 | V7: 45929 | X7: 0 | Y7: =IFERROR(VLOOKUP(reserved_places[[#This Row],[studioID]],studios!$B:$C,2,FALSE),"") -> 1ST CUT DANCE BASE
A8: 6 | B8: 7 | C8: 8 | D8: 7 | E8: 0 | F8: 0 | G8: 0 | H8: 367 | I8: 0 | J8: 8 | K8: 0 | L8: 0 | M8: 0 | N8: 367 | O8: 0 | P8: 9 | Q8: 0 | R8: 0 | S8: 0 | T8: 367 | U8: 0 | V8: 45929 | X8: 0 | Y8: =IFERROR(VLOOKUP(reserved_places[[#This Row],[studioID]],studios!$B:$C,2,FALSE),"") -> CHOREOGRAPHY STUDIO INKARELIS
A9: 7 | B9: 8 | C9: 9 | D9: 7 | E9: 10 | F9: 150 | G9: 1 | H9: 367 | I9: 0 | J9: 8 | K9: 0 | L9: 0 | M9: 0 | N9: 367 | O9: 0 | P9: 9 | Q9: 0 | R9: 0 | S9: 0 | T9: 367 | U9: 0 | V9: 45939.446 | X9: 0 | Y9: =IFERROR(VLOOKUP(reserved_places[[#This Row],[studioID]],studios!$B:$C,2,FALSE),"") -> DE ARTE
A10: 8 | B10: 9 | C10: 10 | D10: 7 | E10: 5 | F10: 65 | G10: 1 | H10: 367 | I10: 0 | J10: 8 | K10: 0 | L10: 0 | M10: 0 | N10: 367 | O10: 0 | P10: 9 | Q10: 0 | R10: 0 | S10: 0 | T10: 367 | U10: 0 | V10: 45938.525 | X10: 0 | Y10: =IFERROR(VLOOKUP(reserved_places[[#This Row],[studioID]],studios!$B:$C,2,FALSE),"") -> DREAM DANCE STUDIO
A11: 9 | B11: 10 | C11: 11 | D11: 7 | E11: 0 | F11: 0 | G11: 0 | H11: 367 | I11: 0 | J11: 8 | K11: 0 | L11: 0 | M11: 0 | N11: 367 | O11: 0 | P11: 9 | Q11: 0 | R11: 0 | S11: 0 | T11: 367 | U11: 0 | V11: 45929 | X11: 0 | Y11: =IFERROR(VLOOKUP(reserved_places[[#This Row],[studioID]],studios!$B:$C,2,FALSE),"") -> DANCE STUDIO STARMIX
A12: 10 | B12: 11 | C12: 12 | D12: 7 | E12: 0 | F12: 0 | G12: 0 | H12: 367 | I12: 0 | J12: 8 | K12: 0 | L12: 0 | M12: 0 | N12: 367 | O12: 0 | P12: 9 | Q12: 0 | R12: 0 | S12: 0 | T12: 367 | U12: 0 | V12: 45929 | X12: 0 | Y12: =IFERROR(VLOOKUP(reserved_places[[#This Row],[studioID]],studios!$B:$C,2,FALSE),"") -> VOU DANCE GROUP
A13: 11 | B13: 12 | C13: 13 | D13: 7 | E13: 3 | F13: 16 | G13: 1 | H13: 367 | I13: 0 | J13: 8 | K13: 0 | L13: 0 | M13: 0 | N13: 367 | O13: 0 | P13: 9 | Q13: 0 | R13: 0 | S13: 0 | T13: 367 | U13: 0 | V13: 45938.545 | X13: 0 | Y13: =IFERROR(VLOOKUP(reserved_places[[#This Row],[studioID]],studios!$B:$C,2,FALSE),"") -> MS DANCE GROUP
... A233: 231 | B233: 236 | C233: 240 | D233: 7 | E233: 0 | F233: 0 | G233: 0 | H233: 367 | I233: 0 | J233: 8 | K233: 0 | L233: 0 | M233: 0 | N233: 367 | O233: 0 | P233: 9 | Q233: 0 | R233: 0 | S233: 0 | T233: 367 | U233: 0 | V233: 45929 | X233: 0 | Y233: =IFERROR(VLOOKUP(reserved_places[[#This Row],[studioID]],studios!$B:$C,2,FALSE),"")
Y234: =IFERROR(VLOOKUP(reserved_places[[#This Row],[studioID]],studios!$B:$C,2,FALSE),"")

Sheet countries
A1: _RowNum | B1: country_ID | C1: name | D1: iso3 | E1: iso2 | F1: numeric_code | G1: phonecode | H1: capital | I1: currency | J1: currency_name | K1: currency_symbol | L1: tld | M1: native | N1: region | O1: region_id | P1: subregion | Q1: subregion_id | R1: nationality | S1: emoji | T1: emojiU | U1: flag | V1: filler
A2: 0 | B2: 1 | C2: Afghanistan | D2: AFG | E2: AF | F2: 4 | G2: 93 | H2: Kabul | I2: AFN | J2: Afghan afghani | K2: ؋ | L2: .af | M2: افغانستان | N2: Asia | O2: 3 | P2: Southern Asia | Q2: 14 | R2: Afghan | S2: 🇦🇫 | T2: U+1F1E6 U+1F1EB
A3: 1 | B3: 2 | C3: Aland Islands | D3: ALA | E3: AX | F3: 248 | G3: 358 | H3: Mariehamn | I3: EUR | J3: Euro | K3: € | L3: .ax | M3: Åland | N3: Europe | O3: 4 | P3: Northern Europe | Q3: 18 | R3: Aland Island | S3: 🇦🇽 | T3: U+1F1E6 U+1F1FD
A4: 2 | B4: 3 | C4: Albania | D4: ALB | E4: AL | F4: 8 | G4: 355 | H4: Tirana | I4: ALL | J4: Albanian lek | K4: Lek | L4: .al | M4: Shqipëria | N4: Europe | O4: 4 | P4: Southern Europe | Q4: 16 | R4: Albanian | S4: 🇦🇱 | T4: U+1F1E6 U+1F1F1
A5: 3 | B5: 4 | C5: Algeria | D5: DZA | E5: DZ | F5: 12 | G5: 213 | H5: Algiers | I5: DZD | J5: Algerian dinar | K5: دج | L5: .dz | M5: الجزائر | N5: Africa | O5: 1 | P5: Northern Africa | Q5: 1 | R5: Algerian | S5: 🇩🇿 | T5: U+1F1E9 U+1F1FF
A6: 4 | B6: 5 | C6: American Samoa | D6: ASM | E6: AS | F6: 16 | G6: 1 | H6: Pago Pago | I6: USD | J6: United States dollar | K6: $ | L6: .as | M6: American Samoa | N6: Oceania | O6: 5 | P6: Polynesia | Q6: 22 | R6: American Samoan | S6: 🇦🇸 | T6: U+1F1E6 U+1F1F8
A7: 5 | B7: 6 | C7: Andorra | D7: AND | E7: AD | F7: 20 | G7: 376 | H7: Andorra la Vella | I7: EUR | J7: Euro | K7: € | L7: .ad | M7: Andorra | N7: Europe | O7: 4 | P7: Southern Europe | Q7: 16 | R7: Andorran | S7: 🇦🇩 | T7: U+1F1E6 U+1F1E9
A8: 6 | B8: 7 | C8: Angola | D8: AGO | E8: AO | F8: 24 | G8: 244 | H8: Luanda | I8: AOA | J8: Angolan kwanza | K8: Kz | L8: .ao | M8: Angola | N8: Africa | O8: 1 | P8: Middle Africa | Q8: 2 | R8: Angolan | S8: 🇦🇴 | T8: U+1F1E6 U+1F1F4
A9: 7 | B9: 8 | C9: Anguilla | D9: AIA | E9: AI | F9: 660 | G9: 1 | H9: The Valley | I9: XCD | J9: Eastern Caribbean dollar | K9: $ | L9: .ai | M9: Anguilla | N9: Americas | O9: 2 | P9: Caribbean | Q9: 7 | R9: Anguillan | S9: 🇦🇮 | T9: U+1F1E6 U+1F1EE
A10: 8 | B10: 9 | C10: Antarctica | D10: ATA | E10: AQ | F10: 10 | G10: 672 | I10: AAD | J10: Antarctican dollar | K10: $ | L10: .aq | M10: Antarctica | N10: Polar | O10: 6 | R10: Antarctic | S10: 🇦🇶 | T10: U+1F1E6 U+1F1F6
A11: 9 | B11: 10 | C11: Antigua and Barbuda | D11: ATG | E11: AG | F11: 28 | G11: 1 | H11: St. John's | I11: XCD | J11: Eastern Caribbean dollar | K11: $ | L11: .ag | M11: Antigua and Barbuda | N11: Americas | O11: 2 | P11: Caribbean | Q11: 7 | R11: Antiguan or Barbudan | S11: 🇦🇬 | T11: U+1F1E6 U+1F1EC
A12: 10 | B12: 11 | C12: Argentina | D12: ARG | E12: AR | F12: 32 | G12: 54 | H12: Buenos Aires | I12: ARS | J12: Argentine peso | K12: $ | L12: .ar | M12: Argentina | N12: Americas | O12: 2 | P12: South America | Q12: 8 | R12: Argentine | S12: 🇦🇷 | T12: U+1F1E6 U+1F1F7
A13: 11 | B13: 12 | C13: Armenia | D13: ARM | E13: AM | F13: 51 | G13: 374 | H13: Yerevan | I13: AMD | J13: Armenian dram | K13: ֏ | L13: .am | M13: Հայաստան | N13: Asia | O13: 3 | P13: Western Asia | Q13: 11 | R13: Armenian | S13: 🇦🇲 | T13: U+1F1E6 U+1F1F2
A14: 12 | B14: 13 | C14: Aruba | D14: ABW | E14: AW | F14: 533 | G14: 297 | H14: Oranjestad | I14: AWG | J14: Aruban florin | K14: ƒ | L14: .aw | M14: Aruba | N14: Americas | O14: 2 | P14: Caribbean | Q14: 7 | R14: Aruban | S14: 🇦🇼 | T14: U+1F1E6 U+1F1FC
A15: 13 | B15: 14 | C15: Australia | D15: AUS | E15: AU | F15: 36 | G15: 61 | H15: Canberra | I15: AUD | J15: Australian dollar | K15: $ | L15: .au | M15: Australia | N15: Oceania | O15: 5 | P15: Australia and New Zealand | Q15: 19 | R15: Australian | S15: 🇦🇺 | T15: U+1F1E6 U+1F1FA
A16: 14 | B16: 15 | C16: Austria | D16: AUT | E16: AT | F16: 40 | G16: 43 | H16: Vienna | I16: EUR | J16: Euro | K16: € | L16: .at | M16: Österreich | N16: Europe | O16: 4 | P16: Western Europe | Q16: 17 | R16: Austrian | S16: 🇦🇹 | T16: U+1F1E6 U+1F1F9
A17: 15 | B17: 16 | C17: Azerbaijan | D17: AZE | E17: AZ | F17: 31 | G17: 994 | H17: Baku | I17: AZN | J17: Azerbaijani manat | K17: m | L17: .az | M17: Azərbaycan | N17: Asia | O17: 3 | P17: Western Asia | Q17: 11 | R17: Azerbaijani, Azeri | S17: 🇦🇿 | T17: U+1F1E6 U+1F1FF
A18: 16 | B18: 17 | C18: Bahrain | D18: BHR | E18: BH | F18: 48 | G18: 973 | H18: Manama | I18: BHD | J18: Bahraini dinar | K18: .د.ب | L18: .bh | M18: ‏البحرين | N18: Asia | O18: 3 | P18: Western Asia | Q18: 11 | R18: Bahraini | S18: 🇧🇭 | T18: U+1F1E7 U+1F1ED
A19: 17 | B19: 18 | C19: Bangladesh | D19: BGD | E19: BD | F19: 50 | G19: 880 | H19: Dhaka | I19: BDT | J19: Bangladeshi taka | K19: ৳ | L19: .bd | M19: Bangladesh | N19: Asia | O19: 3 | P19: Southern Asia | Q19: 14 | R19: Bangladeshi | S19: 🇧🇩 | T19: U+1F1E7 U+1F1E9
A20: 18 | B20: 19 | C20: Barbados | D20: BRB | E20: BB | F20: 52 | G20: 1 | H20: Bridgetown | I20: BBD | J20: Barbadian dollar | K20: Bds$ | L20: .bb | M20: Barbados | N20: Americas | O20: 2 | P20: Caribbean | Q20: 7 | R20: Barbadian | S20: 🇧🇧 | T20: U+1F1E7 U+1F1E7
A21: 19 | B21: 20 | C21: Belarus | D21: BLR | E21: BY | F21: 112 | G21: 375 | H21: Minsk | I21: BYN | J21: Belarusian ruble | K21: Br | L21: .by | M21: Белару́сь | N21: Europe | O21: 4 | P21: Eastern Europe | Q21: 15 | R21: Belarusian | S21: 🇧🇾 | T21: U+1F1E7 U+1F1FE
A22: 20 | B22: 21 | C22: Belgium | D22: BEL | E22: BE | F22: 56 | G22: 32 | H22: Brussels | I22: EUR | J22: Euro | K22: € | L22: .be | M22: België | N22: Europe | O22: 4 | P22: Western Europe | Q22: 17 | R22: Belgian | S22: 🇧🇪 | T22: U+1F1E7 U+1F1EA
... A30: 28 | B30: 29 | C30: Botswana | D30: BWA | E30: BW | F30: 72 | G30: 267 | H30: Gaborone | I30: BWP | J30: Botswana pula | K30: P | L30: .bw | M30: Botswana | N30: Africa | O30: 1 | P30: Southern Africa | Q30: 5 | R30: Motswana, Botswanan | S30: 🇧🇼 | T30: U+1F1E7 U+1F1FC
A31: 29 | B31: 30 | C31: Bouvet Island | D31: BVT | E31: BV | F31: 74 | G31: 55 | I31: NOK | J31: Norwegian krone | K31: ko | L31: .bv | M31: Bouvetøya | R31: Bouvet Island | S31: 🇧🇻 | T31: U+1F1E7 U+1F1FB
A32: 30 | B32: 31 | C32: Brazil | D32: BRA | E32: BR | F32: 76 | G32: 55 | H32: Brasilia | I32: BRL | J32: Brazilian real | K32: R$ | L32: .br | M32: Brasil | N32: Americas | O32: 2 | P32: South America | Q32: 8 | R32: Brazilian | S32: 🇧🇷 | T32: U+1F1E7 U+1F1F7
A33: 31 | B33: 32 | C33: British Indian Ocean Territory | D33: IOT | E33: IO | F33: 86 | G33: 246 | H33: Diego Garcia | I33: USD | J33: United States dollar | K33: $ | L33: .io | M33: British Indian Ocean Territory | N33: Africa | O33: 1 | P33: Eastern Africa | Q33: 4 | R33: BIOT | S33: 🇮🇴 | T33: U+1F1EE U+1F1F4
A34: 32 | B34: 33 | C34: Brunei | D34: BRN | E34: BN | F34: 96 | G34: 673 | H34: Bandar Seri Begawan | I34: BND | J34: Brunei dollar | K34: B$ | L34: .bn | M34: Negara Brunei Darussalam | N34: Asia | O34: 3 | P34: South-Eastern Asia | Q34: 13 | R34: Bruneian | S34: 🇧🇳 | T34: U+1F1E7 U+1F1F3
A35: 33 | B35: 34 | C35: Bulgaria | D35: BGR | E35: BG | F35: 100 | G35: 359 | H35: Sofia | I35: BGN | J35: Bulgarian lev | K35: Лв. | L35: .bg | M35: България | N35: Europe | O35: 4 | P35: Eastern Europe | Q35: 15 | R35: Bulgarian | S35: 🇧🇬 | T35: U+1F1E7 U+1F1EC
A36: 34 | B36: 35 | C36: Burkina Faso | D36: BFA | E36: BF | F36: 854 | G36: 226 | H36: Ouagadougou | I36: XOF | J36: West African CFA franc | K36: CFA | L36: .bf | M36: Burkina Faso | N36: Africa | O36: 1 | P36: Western Africa | Q36: 3 | R36: Burkinabe | S36: 🇧🇫 | T36: U+1F1E7 U+1F1EB
A37: 35 | B37: 36 | C37: Burundi | D37: BDI | E37: BI | F37: 108 | G37: 257 | H37: Bujumbura | I37: BIF | J37: Burundian franc | K37: FBu | L37: .bi | M37: Burundi | N37: Africa | O37: 1 | P37: Eastern Africa | Q37: 4 | R37: Burundian | S37: 🇧🇮 | T37: U+1F1E7 U+1F1EE
A38: 36 | B38: 37 | C38: Cambodia | D38: KHM | E38: KH | F38: 116 | G38: 855 | H38: Phnom Penh | I38: KHR | J38: Cambodian riel | K38: KHR | L38: .kh | M38: Kâmpŭchéa | N38: Asia | O38: 3 | P38: South-Eastern Asia | Q38: 13 | R38: Cambodian | S38: 🇰🇭 | T38: U+1F1F0 U+1F1ED
A39: 37 | B39: 38 | C39: Cameroon | D39: CMR | E39: CM | F39: 120 | G39: 237 | H39: Yaounde | I39: XAF | J39: Central African CFA franc | K39: FCFA | L39: .cm | M39: Cameroon | N39: Africa | O39: 1 | P39: Middle Africa | Q39: 2 | R39: Cameroonian | S39: 🇨🇲 | T39: U+1F1E8 U+1F1F2
A40: 38 | B40: 39 | C40: Canada | D40: CAN | E40: CA | F40: 124 | G40: 1 | H40: Ottawa | I40: CAD | J40: Canadian dollar | K40: $ | L40: .ca | M40: Canada | N40: Americas | O40: 2 | P40: Northern America | Q40: 6 | R40: Canadian | S40: 🇨🇦 | T40: U+1F1E8 U+1F1E6
A41: 39 | B41: 40 | C41: Cape Verde | D41: CPV | E41: CV | F41: 132 | G41: 238 | H41: Praia | I41: CVE | J41: Cape Verdean escudo | K41: $ | L41: .cv | M41: Cabo Verde | N41: Africa | O41: 1 | P41: Western Africa | Q41: 3 | R41: Verdean | S41: 🇨🇻 | T41: U+1F1E8 U+1F1FB
A42: 40 | B42: 41 | C42: Cayman Islands | D42: CYM | E42: KY | F42: 136 | G42: 1 | H42: George Town | I42: KYD | J42: Cayman Islands dollar | K42: $ | L42: .ky | M42: Cayman Islands | N42: Americas | O42: 2 | P42: Caribbean | Q42: 7 | R42: Caymanian | S42: 🇰🇾 | T42: U+1F1F0 U+1F1FE
A43: 41 | B43: 42 | C43: Central African Republic | D43: CAF | E43: CF | F43: 140 | G43: 236 | H43: Bangui | I43: XAF | J43: Central African CFA franc | K43: FCFA | L43: .cf | M43: Ködörösêse tî Bêafrîka | N43: Africa | O43: 1 | P43: Middle Africa | Q43: 2 | R43: Central African | S43: 🇨🇫 | T43: U+1F1E8 U+1F1EB
... A53: 51 | B53: 52 | C53: Costa Rica | D53: CRI | E53: CR | F53: 188 | G53: 506 | H53: San Jose | I53: CRC | J53: Costa Rican colón | K53: ₡ | L53: .cr | M53: Costa Rica | N53: Americas | O53: 2 | P53: Central America | Q53: 9 | R53: Costa Rican | S53: 🇨🇷 | T53: U+1F1E8 U+1F1F7
A54: 52 | B54: 53 | C54: Cote D'Ivoire (Ivory Coast) | D54: CIV | E54: CI | F54: 384 | G54: 225 | H54: Yamoussoukro | I54: XOF | J54: West African CFA franc | K54: CFA | L54: .ci | N54: Africa | O54: 1 | P54: Western Africa | Q54: 3 | R54: Ivorian | S54: 🇨🇮 | T54: U+1F1E8 U+1F1EE
A55: 53 | B55: 54 | C55: Croatia | D55: HRV | E55: HR | F55: 191 | G55: 385 | H55: Zagreb | I55: EUR | J55: Euro | K55: € | L55: .hr | M55: Hrvatska | N55: Europe | O55: 4 | P55: Southern Europe | Q55: 16 | R55: Croatian | S55: 🇭🇷 | T55: U+1F1ED U+1F1F7
A56: 54 | B56: 55 | C56: Cuba | D56: CUB | E56: CU | F56: 192 | G56: 53 | H56: Havana | I56: CUP | J56: Cuban peso | K56: $ | L56: .cu | M56: Cuba | N56: Americas | O56: 2 | P56: Caribbean | Q56: 7 | R56: Cuban | S56: 🇨🇺 | T56: U+1F1E8 U+1F1FA
A57: 55 | B57: 56 | C57: Curaçao | D57: CUW | E57: CW | F57: 531 | G57: 599 | H57: Willemstad | I57: ANG | J57: Netherlands Antillean guilder | K57: ƒ | L57: .cw | M57: Curaçao | N57: Americas | O57: 2 | P57: Caribbean | Q57: 7 | R57: Curacaoan | S57: 🇨🇼 | T57: U+1F1E8 U+1F1FC
A58: 56 | B58: 57 | C58: Cyprus | D58: CYP | E58: CY | F58: 196 | G58: 357 | H58: Nicosia | I58: EUR | J58: Euro | K58: € | L58: .cy | M58: Κύπρος | N58: Europe | O58: 4 | P58: Southern Europe | Q58: 16 | R58: Cypriot | S58: 🇨🇾 | T58: U+1F1E8 U+1F1FE
A59: 57 | B59: 58 | C59: Czech Republic | D59: CZE | E59: CZ | F59: 203 | G59: 420 | H59: Prague | I59: CZK | J59: Czech koruna | K59: Kč | L59: .cz | M59: Česká republika | N59: Europe | O59: 4 | P59: Eastern Europe | Q59: 15 | R59: Czech | S59: 🇨🇿 | T59: U+1F1E8 U+1F1FF
A60: 58 | B60: 59 | C60: Democratic Republic of the Congo | D60: COD | E60: CD | F60: 180 | G60: 243 | H60: Kinshasa | I60: CDF | J60: Congolese Franc | K60: FC | L60: .cd | M60: République démocratique du Congo | N60: Africa | O60: 1 | P60: Middle Africa | Q60: 2 | R60: Congolese | S60: 🇨🇩 | T60: U+1F1E8 U+1F1E9
A61: 59 | B61: 60 | C61: Denmark | D61: DNK | E61: DK | F61: 208 | G61: 45 | H61: Copenhagen | I61: DKK | J61: Danish krone | K61: Kr. | L61: .dk | M61: Danmark | N61: Europe | O61: 4 | P61: Northern Europe | Q61: 18 | R61: Danish | S61: 🇩🇰 | T61: U+1F1E9 U+1F1F0
A62: 60 | B62: 61 | C62: Djibouti | D62: DJI | E62: DJ | F62: 262 | G62: 253 | H62: Djibouti | I62: DJF | J62: Djiboutian franc | K62: Fdj | L62: .dj | M62: Djibouti | N62: Africa | O62: 1 | P62: Eastern Africa | Q62: 4 | R62: Djiboutian | S62: 🇩🇯 | T62: U+1F1E9 U+1F1EF
A63: 61 | B63: 62 | C63: Dominica | D63: DMA | E63: DM | F63: 212 | G63: 1 | H63: Roseau | I63: XCD | J63: Eastern Caribbean dollar | K63: $ | L63: .dm | M63: Dominica | N63: Americas | O63: 2 | P63: Caribbean | Q63: 7 | R63: Dominican | S63: 🇩🇲 | T63: U+1F1E9 U+1F1F2
A64: 62 | B64: 63 | C64: Dominican Republic | D64: DOM | E64: DO | F64: 214 | G64: 1 | H64: Santo Domingo | I64: DOP | J64: Dominican peso | K64: $ | L64: .do | M64: República Dominicana | N64: Americas | O64: 2 | P64: Caribbean | Q64: 7 | R64: Dominican | S64: 🇩🇴 | T64: U+1F1E9 U+1F1F4
A65: 63 | B65: 64 | C65: Ecuador | D65: ECU | E65: EC | F65: 218 | G65: 593 | H65: Quito | I65: USD | J65: United States dollar | K65: $ | L65: .ec | M65: Ecuador | N65: Americas | O65: 2 | P65: South America | Q65: 8 | R65: Ecuadorian | S65: 🇪🇨 | T65: U+1F1EA U+1F1E8
A66: 64 | B66: 65 | C66: Egypt | D66: EGY | E66: EG | F66: 818 | G66: 20 | H66: Cairo | I66: EGP | J66: Egyptian pound | K66: ج.م | L66: .eg | M66: مصر‎ | N66: Africa | O66: 1 | P66: Northern Africa | Q66: 1 | R66: Egyptian | S66: 🇪🇬 | T66: U+1F1EA U+1F1EC
... A96: 94 | B96: 95 | C96: Haiti | D96: HTI | E96: HT | F96: 332 | G96: 509 | H96: Port-au-Prince | I96: HTG | J96: Haitian gourde | K96: G | L96: .ht | M96: Haïti | N96: Americas | O96: 2 | P96: Caribbean | Q96: 7 | R96: Haitian | S96: 🇭🇹 | T96: U+1F1ED U+1F1F9
A97: 95 | B97: 96 | C97: Heard Island and McDonald Islands | D97: HMD | E97: HM | F97: 334 | G97: 672 | I97: AUD | J97: Australian dollar | K97: $ | L97: .hm | M97: Heard Island and McDonald Islands | R97: Heard Island or McDonald Islands | S97: 🇭🇲 | T97: U+1F1ED U+1F1F2
A98: 96 | B98: 97 | C98: Honduras | D98: HND | E98: HN | F98: 340 | G98: 504 | H98: Tegucigalpa | I98: HNL | J98: Honduran lempira | K98: L | L98: .hn | M98: Honduras | N98: Americas | O98: 2 | P98: Central America | Q98: 9 | R98: Honduran | S98: 🇭🇳 | T98: U+1F1ED U+1F1F3
A99: 97 | B99: 98 | C99: Hong Kong S.A.R. | D99: HKG | E99: HK | F99: 344 | G99: 852 | H99: Hong Kong | I99: HKD | J99: Hong Kong dollar | K99: $ | L99: .hk | M99: 香港 | N99: Asia | O99: 3 | P99: Eastern Asia | Q99: 12 | R99: Hong Kong, Hong Kongese | S99: 🇭🇰 | T99: U+1F1ED U+1F1F0
A100: 98 | B100: 99 | C100: Hungary | D100: HUN | E100: HU | F100: 348 | G100: 36 | H100: Budapest | I100: HUF | J100: Hungarian forint | K100: Ft | L100: .hu | M100: Magyarország | N100: Europe | O100: 4 | P100: Eastern Europe | Q100: 15 | R100: Hungarian, Magyar | S100: 🇭🇺 | T100: U+1F1ED U+1F1FA
A101: 99 | B101: 100 | C101: Iceland | D101: ISL | E101: IS | F101: 352 | G101: 354 | H101: Reykjavik | I101: ISK | J101: Icelandic króna | K101: ko | L101: .is | M101: Ísland | N101: Europe | O101: 4 | P101: Northern Europe | Q101: 18 | R101: Icelandic | S101: 🇮🇸 | T101: U+1F1EE U+1F1F8
A102: 100 | B102: 101 | C102: India | D102: IND | E102: IN | F102: 356 | G102: 91 | H102: New Delhi | I102: INR | J102: Indian rupee | K102: ₹ | L102: .in | M102: भारत | N102: Asia | O102: 3 | P102: Southern Asia | Q102: 14 | R102: Indian | S102: 🇮🇳 | T102: U+1F1EE U+1F1F3
A103: 101 | B103: 102 | C103: Indonesia | D103: IDN | E103: ID | F103: 360 | G103: 62 | H103: Jakarta | I103: IDR | J103: Indonesian rupiah | K103: Rp | L103: .id | M103: Indonesia | N103: Asia | O103: 3 | P103: South-Eastern Asia | Q103: 13 | R103: Indonesian | S103: 🇮🇩 | T103: U+1F1EE U+1F1E9
A104: 102 | B104: 103 | C104: Iran | D104: IRN | E104: IR | F104: 364 | G104: 98 | H104: Tehran | I104: IRR | J104: Iranian rial | K104: ﷼ | L104: .ir | M104: ایران | N104: Asia | O104: 3 | P104: Southern Asia | Q104: 14 | R104: Iranian, Persian | S104: 🇮🇷 | T104: U+1F1EE U+1F1F7
A105: 103 | B105: 104 | C105: Iraq | D105: IRQ | E105: IQ | F105: 368 | G105: 964 | H105: Baghdad | I105: IQD | J105: Iraqi dinar | K105: د.ع | L105: .iq | M105: العراق | N105: Asia | O105: 3 | P105: Western Asia | Q105: 11 | R105: Iraqi | S105: 🇮🇶 | T105: U+1F1EE U+1F1F6
A106: 104 | B106: 105 | C106: Ireland | D106: IRL | E106: IE | F106: 372 | G106: 353 | H106: Dublin | I106: EUR | J106: Euro | K106: € | L106: .ie | M106: Éire | N106: Europe | O106: 4 | P106: Northern Europe | Q106: 18 | R106: Irish | S106: 🇮🇪 | T106: U+1F1EE U+1F1EA
A107: 105 | B107: 106 | C107: Israel | D107: ISR | E107: IL | F107: 376 | G107: 972 | H107: Jerusalem | I107: ILS | J107: Israeli new shekel | K107: ₪ | L107: .il | M107: יִשְׂרָאֵל | N107: Asia | O107: 3 | P107: Western Asia | Q107: 11 | R107: Israeli | S107: 🇮🇱 | T107: U+1F1EE U+1F1F1
A108: 106 | B108: 107 | C108: Italy | D108: ITA | E108: IT | F108: 380 | G108: 39 | H108: Rome | I108: EUR | J108: Euro | K108: € | L108: .it | M108: Italia | N108: Europe | O108: 4 | P108: Southern Europe | Q108: 16 | R108: Italian | S108: 🇮🇹 | T108: U+1F1EE U+1F1F9
A109: 107 | B109: 108 | C109: Jamaica | D109: JAM | E109: JM | F109: 388 | G109: 1 | H109: Kingston | I109: JMD | J109: Jamaican dollar | K109: J$ | L109: .jm | M109: Jamaica | N109: Americas | O109: 2 | P109: Caribbean | Q109: 7 | R109: Jamaican | S109: 🇯🇲 | T109: U+1F1EF U+1F1F2
... A224: 222 | B224: 223 | C224: Togo | D224: TGO | E224: TG | F224: 768 | G224: 228 | H224: Lome | I224: XOF | J224: West African CFA franc | K224: CFA | L224: .tg | M224: Togo | N224: Africa | O224: 1 | P224: Western Africa | Q224: 3 | R224: Togolese | S224: 🇹🇬 | T224: U+1F1F9 U+1F1EC
A225: 223 | B225: 224 | C225: Tokelau | D225: TKL | E225: TK | F225: 772 | G225: 690 | I225: NZD | J225: New Zealand dollar | K225: $ | L225: .tk | M225: Tokelau | N225: Oceania | O225: 5 | P225: Polynesia | Q225: 22 | R225: Tokelauan | S225: 🇹🇰 | T225: U+1F1F9 U+1F1F0
A226: 224 | B226: 225 | C226: Tonga | D226: TON | E226: TO | F226: 776 | G226: 676 | H226: Nuku'alofa | I226: TOP | J226: Tongan paʻanga | K226: $ | L226: .to | M226: Tonga | N226: Oceania | O226: 5 | P226: Polynesia | Q226: 22 | R226: Tongan | S226: 🇹🇴 | T226: U+1F1F9 U+1F1F4
A227: 225 | B227: 226 | C227: Trinidad and Tobago | D227: TTO | E227: TT | F227: 780 | G227: 1 | H227: Port of Spain | I227: TTD | J227: Trinidad and Tobago dollar | K227: $ | L227: .tt | M227: Trinidad and Tobago | N227: Americas | O227: 2 | P227: Caribbean | Q227: 7 | R227: Trinidadian or Tobagonian | S227: 🇹🇹 | T227: U+1F1F9 U+1F1F9
A228: 226 | B228: 227 | C228: Tunisia | D228: TUN | E228: TN | F228: 788 | G228: 216 | H228: Tunis | I228: TND | J228: Tunisian dinar | K228: ت.د | L228: .tn | M228: تونس | N228: Africa | O228: 1 | P228: Northern Africa | Q228: 1 | R228: Tunisian | S228: 🇹🇳 | T228: U+1F1F9 U+1F1F3
A229: 227 | B229: 228 | C229: Türkiye | D229: TUR | E229: TR | F229: 792 | G229: 90 | H229: Ankara | I229: TRY | J229: Turkish lira | K229: ₺ | L229: .tr | M229: Türkiye | N229: Asia | O229: 3 | P229: Western Asia | Q229: 11 | R229: Turkish | S229: 🇹🇷 | T229: U+1F1F9 U+1F1F7
A230: 228 | B230: 229 | C230: Turkmenistan | D230: TKM | E230: TM | F230: 795 | G230: 993 | H230: Ashgabat | I230: TMT | J230: Turkmenistan manat | K230: T | L230: .tm | M230: Türkmenistan | N230: Asia | O230: 3 | P230: Central Asia | Q230: 10 | R230: Turkmen | S230: 🇹🇲 | T230: U+1F1F9 U+1F1F2
A231: 229 | B231: 230 | C231: Turks and Caicos Islands | D231: TCA | E231: TC | F231: 796 | G231: 1 | H231: Cockburn Town | I231: USD | J231: United States dollar | K231: $ | L231: .tc | M231: Turks and Caicos Islands | N231: Americas | O231: 2 | P231: Caribbean | Q231: 7 | R231: Turks and Caicos Island | S231: 🇹🇨 | T231: U+1F1F9 U+1F1E8
A232: 230 | B232: 231 | C232: Tuvalu | D232: TUV | E232: TV | F232: 798 | G232: 688 | H232: Funafuti | I232: AUD | J232: Australian dollar | K232: $ | L232: .tv | M232: Tuvalu | N232: Oceania | O232: 5 | P232: Polynesia | Q232: 22 | R232: Tuvaluan | S232: 🇹🇻 | T232: U+1F1F9 U+1F1FB
A233: 231 | B233: 232 | C233: Uganda | D233: UGA | E233: UG | F233: 800 | G233: 256 | H233: Kampala | I233: UGX | J233: Ugandan shilling | K233: USh | L233: .ug | M233: Uganda | N233: Africa | O233: 1 | P233: Eastern Africa | Q233: 4 | R233: Ugandan | S233: 🇺🇬 | T233: U+1F1FA U+1F1EC
A234: 232 | B234: 233 | C234: Ukraine | D234: UKR | E234: UA | F234: 804 | G234: 380 | H234: Kyiv | I234: UAH | J234: Ukrainian hryvnia | K234: ₴ | L234: .ua | M234: Україна | N234: Europe | O234: 4 | P234: Eastern Europe | Q234: 15 | R234: Ukrainian | S234: 🇺🇦 | T234: U+1F1FA U+1F1E6
A235: 233 | B235: 234 | C235: United Arab Emirates | D235: ARE | E235: AE | F235: 784 | G235: 971 | H235: Abu Dhabi | I235: AED | J235: United Arab Emirates dirham | K235: إ.د | L235: .ae | M235: دولة الإمارات العربية المتحدة | N235: Asia | O235: 3 | P235: Western Asia | Q235: 11 | R235: Emirati, Emirian, Emiri | S235: 🇦🇪 | T235: U+1F1E6 U+1F1EA
A236: 234 | B236: 235 | C236: United Kingdom | D236: GBR | E236: GB | F236: 826 | G236: 44 | H236: London | I236: GBP | J236: British pound | K236: £ | L236: .uk | M236: United Kingdom | N236: Europe | O236: 4 | P236: Northern Europe | Q236: 18 | R236: British, UK | S236: 🇬🇧 | T236: U+1F1EC U+1F1E7
A237: 235 | B237: 236 | C237: United States | D237: USA | E237: US | F237: 840 | G237: 1 | H237: Washington | I237: USD | J237: United States dollar | K237: $ | L237: .us | M237: United States | N237: Americas | O237: 2 | P237: Northern America | Q237: 6 | R237: American | S237: 🇺🇸 | T237: U+1F1FA U+1F1F8
A238: 236 | B238: 237 | C238: United States Minor Outlying Islands | D238: UMI | E238: UM | F238: 581 | G238: 1 | I238: USD | J238: United States dollar | K238: $ | L238: .us | M238: United States Minor Outlying Islands | N238: Americas | O238: 2 | P238: Northern America | Q238: 6 | R238: American | S238: 🇺🇲 | T238: U+1F1FA U+1F1F2
A239: 237 | B239: 238 | C239: Uruguay | D239: URY | E239: UY | F239: 858 | G239: 598 | H239: Montevideo | I239: UYU | J239: Uruguayan peso | K239: $ | L239: .uy | M239: Uruguay | N239: Americas | O239: 2 | P239: South America | Q239: 8 | R239: Uruguayan | S239: 🇺🇾 | T239: U+1F1FA U+1F1FE
A240: 238 | B240: 239 | C240: Uzbekistan | D240: UZB | E240: UZ | F240: 860 | G240: 998 | H240: Tashkent | I240: UZS | J240: Uzbekistani soʻm | K240: лв | L240: .uz | M240: O‘zbekiston | N240: Asia | O240: 3 | P240: Central Asia | Q240: 10 | R240: Uzbekistani, Uzbek | S240: 🇺🇿 | T240: U+1F1FA U+1F1FF
A241: 239 | B241: 240 | C241: Vanuatu | D241: VUT | E241: VU | F241: 548 | G241: 678 | H241: Port Vila | I241: VUV | J241: Vanuatu vatu | K241: VT | L241: .vu | M241: Vanuatu | N241: Oceania | O241: 5 | P241: Melanesia | Q241: 20 | R241: Ni-Vanuatu, Vanuatuan | S241: 🇻🇺 | T241: U+1F1FB U+1F1FA
A242: 240 | B242: 241 | C242: Vatican City State (Holy See) | D242: VAT | E242: VA | F242: 336 | G242: 379 | H242: Vatican City | I242: EUR | J242: Euro | K242: € | L242: .va | M242: Vaticano | N242: Europe | O242: 4 | P242: Southern Europe | Q242: 16 | R242: Vatican | S242: 🇻🇦 | T242: U+1F1FB U+1F1E6
A243: 241 | B243: 242 | C243: Venezuela | D243: VEN | E243: VE | F243: 862 | G243: 58 | H243: Caracas | I243: VES | J243: Bolívar | K243: Bs | L243: .ve | M243: Venezuela | N243: Americas | O243: 2 | P243: South America | Q243: 8 | R243: Venezuelan | S243: 🇻🇪 | T243: U+1F1FB U+1F1EA
A244: 242 | B244: 243 | C244: Vietnam | D244: VNM | E244: VN | F244: 704 | G244: 84 | H244: Hanoi | I244: VND | J244: Vietnamese đồng | K244: ₫ | L244: .vn | M244: Việt Nam | N244: Asia | O244: 3 | P244: South-Eastern Asia | Q244: 13 | R244: Vietnamese | S244: 🇻🇳 | T244: U+1F1FB U+1F1F3
A245: 243 | B245: 244 | C245: Virgin Islands (British) | D245: VGB | E245: VG | F245: 92 | G245: 1 | H245: Road Town | I245: USD | J245: United States dollar | K245: $ | L245: .vg | M245: British Virgin Islands | N245: Americas | O245: 2 | P245: Caribbean | Q245: 7 | R245: British Virgin Island | S245: 🇻🇬 | T245: U+1F1FB U+1F1EC
A246: 244 | B246: 245 | C246: Virgin Islands (US) | D246: VIR | E246: VI | F246: 850 | G246: 1 | H246: Charlotte Amalie | I246: USD | J246: United States dollar | K246: $ | L246: .vi | M246: United States Virgin Islands | N246: Americas | O246: 2 | P246: Caribbean | Q246: 7 | R246: U.S. Virgin Island | S246: 🇻🇮 | T246: U+1F1FB U+1F1EE
A247: 245 | B247: 246 | C247: Wallis and Futuna Islands | D247: WLF | E247: WF | F247: 876 | G247: 681 | H247: Mata Utu | I247: XPF | J247: CFP franc | K247: ₣ | L247: .wf | M247: Wallis et Futuna | N247: Oceania | O247: 5 | P247: Polynesia | Q247: 22 | R247: Wallis and Futuna, Wallisian or Futunan | S247: 🇼🇫 | T247: U+1F1FC U+1F1EB
A248: 246 | B248: 247 | C248: Western Sahara | D248: ESH | E248: EH | F248: 732 | G248: 212 | H248: El-Aaiun | I248: MAD | J248: Moroccan dirham | K248: MAD | L248: .eh | M248: الصحراء الغربية | N248: Africa | O248: 1 | P248: Northern Africa | Q248: 1 | R248: Sahrawi, Sahrawian, Sahraouian | S248: 🇪🇭 | T248: U+1F1EA U+1F1ED
A249: 247 | B249: 248 | C249: Yemen | D249: YEM | E249: YE | F249: 887 | G249: 967 | H249: Sanaa | I249: YER | J249: Yemeni rial | K249: ﷼ | L249: .ye | M249: اليَمَن | N249: Asia | O249: 3 | P249: Western Asia | Q249: 11 | R249: Yemeni | S249: 🇾🇪 | T249: U+1F1FE U+1F1EA
A250: 248 | B250: 249 | C250: Zambia | D250: ZMB | E250: ZM | F250: 894 | G250: 260 | H250: Lusaka | I250: ZMW | J250: Zambian kwacha | K250: ZK | L250: .zm | M250: Zambia | N250: Africa | O250: 1 | P250: Southern Africa | Q250: 5 | R250: Zambian | S250: 🇿🇲 | T250: U+1F1FF U+1F1F2
A251: 249 | B251: 250 | C251: Zimbabwe | D251: ZWE | E251: ZW | F251: 716 | G251: 263 | H251: Harare | I251: ZWL | J251: Zimbabwe Dollar | K251: $ | L251: .zw | M251: Zimbabwe | N251: Africa | O251: 1 | P251: Eastern Africa | Q251: 4 | R251: Zimbabwean | S251: 🇿🇼 | T251: U+1F1FF U+1F1FC

Sheet SaveToDB_Data
A1: ID
A2: Start Fields of object [s4d_2025.dbo.studios] on server [2.59.119.221]
D3: studio_ID | E3: 1 | G3: FALSE | H3: TRUE | I3: FALSE | J3: int | L3: 10 | M3: 0 | N3: TRUE | O3: studio_ID | V3: FALSE | W3: TRUE
D4: studioname | E4: 2 | G4: FALSE | H4: FALSE | I4: FALSE | J4: nvarchar | K4: 50 | N4: FALSE | O4: studioname | V4: FALSE | W4: TRUE
D5: contact | E5: 3 | G5: TRUE | H5: FALSE | I5: FALSE | J5: nvarchar | K5: 50 | N5: FALSE | O5: contact | V5: FALSE | W5: TRUE
D6: fname | E6: 4 | G6: TRUE | H6: FALSE | I6: FALSE | J6: nvarchar | K6: 30 | N6: FALSE | O6: fname | V6: FALSE | W6: TRUE
D7: surname | E7: 5 | G7: TRUE | H7: FALSE | I7: FALSE | J7: nvarchar | K7: 30 | N7: FALSE | O7: surname | V7: FALSE | W7: TRUE
D8: email | E8: 6 | G8: TRUE | H8: FALSE | I8: FALSE | J8: nvarchar | K8: 80 | N8: FALSE | O8: email | V8: FALSE | W8: TRUE
D9: mobile | E9: 7 | G9: TRUE | H9: FALSE | I9: FALSE | J9: nvarchar | K9: 20 | N9: FALSE | O9: mobile | V9: FALSE | W9: TRUE
D10: city | E10: 8 | G10: TRUE | H10: FALSE | I10: FALSE | J10: nvarchar | K10: 50 | N10: FALSE | O10: city | V10: FALSE | W10: TRUE
D11: countryID | E11: 9 | G11: TRUE | H11: FALSE | I11: FALSE | J11: int | L11: 10 | M11: 0 | N11: FALSE | O11: countryID | V11: FALSE | W11: TRUE
D12: instagram | E12: 10 | G12: TRUE | H12: FALSE | I12: FALSE | J12: nvarchar | K12: 50 | N12: FALSE | O12: instagram | V12: FALSE | W12: TRUE
D13: pincode | E13: 11 | G13: TRUE | H13: FALSE | I13: FALSE | J13: int | L13: 10 | M13: 0 | N13: FALSE | O13: pincode | V13: FALSE | W13: TRUE
D14: datecreated | E14: 12 | G14: TRUE | H14: FALSE | I14: FALSE | J14: datetime | L14: 3 | N14: FALSE | O14: datecreated | V14: FALSE | W14: TRUE
D15: lastupdated | E15: 13 | G15: TRUE | H15: FALSE | I15: FALSE | J15: datetime | L15: 3 | N15: FALSE | O15: lastupdated | V15: FALSE | W15: TRUE
D16: ipaddress | E16: 14 | G16: TRUE | H16: FALSE | I16: FALSE | J16: nvarchar | K16: 16 | N16: FALSE | O16: ipaddress | V16: FALSE | W16: TRUE
D17: sessionID | E17: 15 | G17: TRUE | H17: FALSE | I17: FALSE | J17: bigint | L17: 19 | M17: 0 | N17: FALSE | O17: sessionID | V17: FALSE | W17: TRUE
D18: secureno | E18: 16 | G18: TRUE | H18: FALSE | I18: FALSE | J18: bigint | L18: 19 | M18: 0 | N18: FALSE | O18: secureno | V18: FALSE | W18: TRUE
D19: duplicates | E19: 17 | G19: TRUE | H19: FALSE | I19: FALSE | J19: nvarchar | K19: 140 | N19: FALSE | O19: duplicates | V19: FALSE | W19: TRUE
D20: bulk_link | E20: 18 | G20: TRUE | H20: FALSE | I20: FALSE | J20: varchar | K20: -1 | N20: FALSE | O20: bulk_link | V20: FALSE | W20: TRUE
D21: bulk_uploaded | E21: 19 | F21: ((0)) | G21: TRUE | H21: FALSE | I21: FALSE | J21: bit | N21: FALSE | O21: bulk_uploaded | V21: FALSE | W21: TRUE
D22: filler | E22: 20 | G22: TRUE | H22: FALSE | I22: FALSE | J22: nchar | K22: 1 | N22: FALSE | O22: filler | V22: FALSE | W22: TRUE
A23: End Fields of object [s4d_2025.dbo.studios] on server [2.59.119.221]
A24: Start Last Connect to DB values
A25: 2.59.119.221 | B25: FALSE | C25: saf_s4d | D25: s4d_2025 | E25: (Default) | F25: Provider=SQLOLEDB
A26: End Last Connect to DB values
A27: Start Objects of query object [s4d_2025.(Default)] on server [2.59.119.221]
C28: dbo | D28: acts | E28: TABLE | I28: dbo.acts
C29: dbo | D29: countries | E29: TABLE | I29: dbo.countries
C30: dbo | D30: dancers | E30: TABLE | I30: dbo.dancers
C31: dbo | D31: reserved_places | E31: TABLE | I31: dbo.reserved_places
C32: dbo | D32: studios | E32: TABLE | I32: dbo.studios
A33: End Objects of query object [s4d_2025.(Default)] on server [2.59.119.221]
A34: Start ListObjects
A35: studios | B35: (Default) | C35: FALSE | D35: dbo.studios | E35: TABLE | W35: dbo.studios | Z35: FALSE | AA35: dbo.studios | AH35: dd/MM/yyyy | AI35: HH:mm:ss | AJ35: _none_ | AK35: FALSE | AL35: FALSE
A36: acts | B36: (Default) | C36: FALSE | D36: dbo.acts | E36: TABLE | W36: dbo.acts | Z36: FALSE | AA36: dbo.acts | AH36: dd/MM/yyyy | AI36: HH:mm:ss | AJ36: _none_ | AK36: FALSE | AL36: FALSE
A37: dancers | B37: (Default) | C37: FALSE | D37: dbo.dancers | E37: TABLE | W37: dbo.dancers | Z37: FALSE | AA37: dbo.dancers | AE37: en-GB | AF37: . | AG37: , | AH37: dd/MM/yyyy | AI37: HH:mm:ss | AJ37: _none_ | AK37: FALSE | AL37: FALSE
A38: reserved_places | B38: (Default) | C38: FALSE | D38: dbo.reserved_places | E38: TABLE | W38: dbo.reserved_places | Z38: FALSE | AA38: dbo.reserved_places | AE38: en-GB | AF38: . | AG38: , | AH38: dd/MM/yyyy | AI38: HH:mm:ss | AJ38: _none_ | AK38: FALSE | AL38: FALSE
A39: countries | B39: (Default) | C39: FALSE | D39: dbo.countries | E39: TABLE | W39: dbo.countries | Z39: FALSE | AA39: dbo.countries | AE39: en-GB | AF39: . | AG39: , | AH39: dd/MM/yyyy | AI39: HH:mm:ss | AJ39: _none_ | AK39: FALSE | AL39: FALSE
A40: End ListObjects
A41: Start Fields of object [s4d_2025.dbo.acts] on server [2.59.119.221]
D42: act_ID | E42: 1 | G42: FALSE | H42: TRUE | I42: FALSE | J42: int | L42: 10 | M42: 0 | N42: TRUE | O42: act_ID | V42: FALSE | W42: TRUE
D43: eventID | E43: 2 | G43: FALSE | H43: FALSE | I43: FALSE | J43: int | L43: 10 | M43: 0 | N43: FALSE | O43: eventID | V43: FALSE | W43: TRUE
D44: eventname | E44: 3 | G44: TRUE | H44: FALSE | I44: FALSE | J44: nvarchar | K44: 21 | N44: FALSE | O44: eventname | V44: FALSE | W44: TRUE
D45: studioID | E45: 4 | G45: FALSE | H45: FALSE | I45: FALSE | J45: int | L45: 10 | M45: 0 | N45: FALSE | O45: studioID | V45: FALSE | W45: TRUE
D46: teamname | E46: 5 | G46: TRUE | H46: FALSE | I46: FALSE | J46: nvarchar | K46: 50 | N46: FALSE | O46: teamname | V46: FALSE | W46: TRUE
D47: actname | E47: 6 | G47: FALSE | H47: FALSE | I47: FALSE | J47: nvarchar | K47: 50 | N47: FALSE | O47: actname | V47: FALSE | W47: TRUE
D48: act_format | E48: 7 | G48: TRUE | H48: FALSE | I48: FALSE | J48: nchar | K48: 5 | N48: FALSE | O48: act_format | V48: FALSE | W48: TRUE
D49: act_type | E49: 8 | G49: TRUE | H49: FALSE | I49: FALSE | J49: int | L49: 10 | M49: 0 | N49: FALSE | O49: act_type | V49: FALSE | W49: TRUE
D50: comp_numbers | E50: 9 | G50: TRUE | H50: FALSE | I50: FALSE | J50: int | L50: 10 | M50: 0 | N50: FALSE | O50: comp_numbers | V50: FALSE | W50: TRUE
D51: act_nomination | E51: 10 | G51: TRUE | H51: FALSE | I51: FALSE | J51: nvarchar | K51: 21 | N51: FALSE | O51: act_nomination | V51: FALSE | W51: TRUE
D52: act_agegroup | E52: 11 | G52: TRUE | H52: FALSE | I52: FALSE | J52: nchar | K52: 9 | N52: FALSE | O52: act_agegroup | V52: FALSE | W52: TRUE
D53: act_division | E53: 12 | G53: TRUE | H53: FALSE | I53: FALSE | J53: nchar | K53: 10 | N53: FALSE | O53: act_division | V53: FALSE | W53: TRUE
D54: act_min_age | E54: 13 | G54: TRUE | H54: FALSE | I54: FALSE | J54: int | L54: 10 | M54: 0 | N54: FALSE | O54: act_min_age | V54: FALSE | W54: TRUE
D55: act_max_age | E55: 14 | G55: TRUE | H55: FALSE | I55: FALSE | J55: int | L55: 10 | M55: 0 | N55: FALSE | O55: act_max_age | V55: FALSE | W55: TRUE
D56: mixedage | E56: 15 | G56: TRUE | H56: FALSE | I56: FALSE | J56: nchar | K56: 7 | N56: FALSE | O56: mixedage | V56: FALSE | W56: TRUE
D57: notes | E57: 16 | G57: TRUE | H57: FALSE | I57: FALSE | J57: nvarchar | K57: -1 | N57: FALSE | O57: notes | V57: FALSE | W57: TRUE
D58: datecreated | E58: 17 | G58: TRUE | H58: FALSE | I58: FALSE | J58: datetime | L58: 3 | N58: FALSE | O58: datecreated | V58: FALSE | W58: TRUE
D59: lastupdated | E59: 18 | G59: TRUE | H59: FALSE | I59: FALSE | J59: datetime | L59: 3 | N59: FALSE | O59: lastupdated | V59: FALSE | W59: TRUE
D60: duplicates | E60: 19 | G60: TRUE | H60: FALSE | I60: FALSE | J60: nvarchar | K60: 140 | N60: FALSE | O60: duplicates | V60: FALSE | W60: TRUE
D61: filler | E61: 20 | G61: TRUE | H61: FALSE | I61: FALSE | J61: nchar | K61: 1 | N61: FALSE | O61: filler | V61: FALSE | W61: TRUE
A62: End Fields of object [s4d_2025.dbo.acts] on server [2.59.119.221]
A63: Start Fields of object [s4d_2025.dbo.dancers] on server [2.59.119.221]
D64: dancer_ID | E64: 1 | G64: FALSE | H64: TRUE | I64: FALSE | J64: int | L64: 10 | M64: 0 | N64: TRUE | O64: dancer_ID | V64: FALSE | W64: TRUE
D65: studioID | E65: 2 | G65: FALSE | H65: FALSE | I65: FALSE | J65: int | L65: 10 | M65: 0 | N65: FALSE | O65: studioID | V65: FALSE | W65: TRUE
D66: dancer | E66: 3 | G66: FALSE | H66: FALSE | I66: FALSE | J66: nvarchar | K66: 50 | N66: FALSE | O66: dancer | V66: FALSE | W66: TRUE
D67: dateofbirth | E67: 4 | G67: TRUE | H67: FALSE | I67: FALSE | J67: date | L67: 0 | N67: FALSE | O67: dateofbirth | V67: FALSE | W67: TRUE
D68: dd_dob | E68: 5 | G68: TRUE | H68: FALSE | I68: FALSE | J68: int | L68: 10 | M68: 0 | N68: FALSE | O68: dd_dob | V68: FALSE | W68: TRUE
D69: mm_dob | E69: 6 | G69: TRUE | H69: FALSE | I69: FALSE | J69: int | L69: 10 | M69: 0 | N69: FALSE | O69: mm_dob | V69: FALSE | W69: TRUE
D70: year_dob | E70: 7 | G70: TRUE | H70: FALSE | I70: FALSE | J70: int | L70: 10 | M70: 0 | N70: FALSE | O70: year_dob | V70: FALSE | W70: TRUE
D71: datecreated | E71: 8 | G71: TRUE | H71: FALSE | I71: FALSE | J71: datetime | L71: 3 | N71: FALSE | O71: datecreated | V71: FALSE | W71: TRUE
D72: lastupdated | E72: 9 | G72: TRUE | H72: FALSE | I72: FALSE | J72: datetime | L72: 3 | N72: FALSE | O72: lastupdated | V72: FALSE | W72: TRUE
D73: duplicates | E73: 10 | G73: TRUE | H73: FALSE | I73: FALSE | J73: nvarchar | K73: 140 | N73: FALSE | O73: duplicates | V73: FALSE | W73: TRUE
D74: filler | E74: 11 | G74: TRUE | H74: FALSE | I74: FALSE | J74: nchar | K74: 1 | N74: FALSE | O74: filler | V74: FALSE | W74: TRUE
A75: End Fields of object [s4d_2025.dbo.dancers] on server [2.59.119.221]
A76: Start Fields of object [s4d_2025.dbo.reserved_places] on server [2.59.119.221]
D77: reserveID | E77: 1 | G77: FALSE | H77: TRUE | I77: FALSE | J77: int | L77: 10 | M77: 0 | N77: TRUE | O77: reserveID | V77: FALSE | W77: TRUE
D78: studioID | E78: 2 | G78: FALSE | H78: FALSE | I78: FALSE | J78: int | L78: 10 | M78: 0 | N78: FALSE | O78: studioID | V78: FALSE | W78: TRUE
D79: event1 | E79: 3 | F79: ((7)) | G79: TRUE | H79: FALSE | I79: FALSE | J79: int | L79: 10 | M79: 0 | N79: FALSE | O79: event1 | V79: FALSE | W79: TRUE
D80: riga_acts | E80: 4 | G80: TRUE | H80: FALSE | I80: FALSE | J80: int | L80: 10 | M80: 0 | N80: FALSE | O80: riga_acts | V80: FALSE | W80: TRUE
D81: block1 | E81: 5 | F81: ((0)) | G81: TRUE | H81: FALSE | I81: FALSE | J81: int | L81: 10 | M81: 0 | N81: FALSE | O81: block1 | V81: FALSE | W81: TRUE
D82: riga_dancers | E82: 6 | G82: TRUE | H82: FALSE | I82: FALSE | J82: int | L82: 10 | M82: 0 | N82: FALSE | O82: riga_dancers | V82: FALSE | W82: TRUE
D83: riga_changed | E83: 7 | G83: TRUE | H83: FALSE | I83: FALSE | J83: int | L83: 10 | M83: 0 | N83: FALSE | O83: riga_changed | V83: FALSE | W83: TRUE
D84: riga_datepaid | E84: 8 | G84: TRUE | H84: FALSE | I84: FALSE | J84: datetime | L84: 3 | N84: FALSE | O84: riga_datepaid | V84: FALSE | W84: TRUE
D85: riga_money | E85: 9 | G85: TRUE | H85: FALSE | I85: FALSE | J85: money | L85: 19 | M85: 4 | N85: FALSE | O85: riga_money | V85: FALSE | W85: TRUE
D86: event2 | E86: 10 | F86: ((8)) | G86: TRUE | H86: FALSE | I86: FALSE | J86: int | L86: 10 | M86: 0 | N86: FALSE | O86: event2 | V86: FALSE | W86: TRUE
D87: belek_acts | E87: 11 | G87: TRUE | H87: FALSE | I87: FALSE | J87: int | L87: 10 | M87: 0 | N87: FALSE | O87: belek_acts | V87: FALSE | W87: TRUE
D88: belek_dancers | E88: 12 | G88: TRUE | H88: FALSE | I88: FALSE | J88: int | L88: 10 | M88: 0 | N88: FALSE | O88: belek_dancers | V88: FALSE | W88: TRUE
D89: belek_changed | E89: 13 | G89: TRUE | H89: FALSE | I89: FALSE | J89: int | L89: 10 | M89: 0 | N89: FALSE | O89: belek_changed | V89: FALSE | W89: TRUE
D90: belek_datepaid | E90: 14 | G90: TRUE | H90: FALSE | I90: FALSE | J90: datetime | L90: 3 | N90: FALSE | O90: belek_datepaid | V90: FALSE | W90: TRUE
D91: belek_money | E91: 15 | G91: TRUE | H91: FALSE | I91: FALSE | J91: money | L91: 19 | M91: 4 | N91: FALSE | O91: belek_money | V91: FALSE | W91: TRUE
D92: event3 | E92: 16 | F92: ((9)) | G92: TRUE | H92: FALSE | I92: FALSE | J92: int | L92: 10 | M92: 0 | N92: FALSE | O92: event3 | V92: FALSE | W92: TRUE
D93: wod_acts | E93: 17 | G93: TRUE | H93: FALSE | I93: FALSE | J93: int | L93: 10 | M93: 0 | N93: FALSE | O93: wod_acts | V93: FALSE | W93: TRUE
D94: wod_dancers | E94: 18 | G94: TRUE | H94: FALSE | I94: FALSE | J94: int | L94: 10 | M94: 0 | N94: FALSE | O94: wod_dancers | V94: FALSE | W94: TRUE
D95: wod_changed | E95: 19 | G95: TRUE | H95: FALSE | I95: FALSE | J95: int | L95: 10 | M95: 0 | N95: FALSE | O95: wod_changed | V95: FALSE | W95: TRUE
D96: wod_datepaid | E96: 20 | G96: TRUE | H96: FALSE | I96: FALSE | J96: datetime | L96: 3 | N96: FALSE | O96: wod_datepaid | V96: FALSE | W96: TRUE
D97: wod_money | E97: 21 | G97: TRUE | H97: FALSE | I97: FALSE | J97: money | L97: 19 | M97: 4 | N97: FALSE | O97: wod_money | V97: FALSE | W97: TRUE
D98: lastupdated | E98: 22 | G98: TRUE | H98: FALSE | I98: FALSE | J98: datetime | L98: 3 | N98: FALSE | O98: lastupdated | V98: FALSE | W98: TRUE
D99: eof | E99: 23 | G99: FALSE | H99: FALSE | I99: FALSE | J99: nchar | K99: 1 | N99: FALSE | O99: eof | V99: FALSE | W99: TRUE
A100: End Fields of object [s4d_2025.dbo.reserved_places] on server [2.59.119.221]
...

Sheet SaveToDB_LoadedID
A1: ID
A2: Start IDs of object [dbo.countries] on sheet [countries]
A3: _RowNum | B3: country_ID | C3: name | D3: iso3 | E3: iso2 | F3: numeric_code | G3: phonecode | H3: capital | I3: currency | J3: currency_name | K3: currency_symbol | L3: tld | M3: native | N3: region | O3: region_id | P3: subregion | Q3: subregion_id | R3: nationality | S3: emoji | T3: emojiU | U3: flag | V3: filler
A4: 0 | B4: 1 | C4: Afghanistan | D4: AFG | E4: AF | F4: 4 | G4: 93 | H4: Kabul | I4: AFN | J4: Afghan afghani | K4: ؋ | L4: .af | M4: افغانستان | N4: Asia | O4: 3 | P4: Southern Asia | Q4: 14 | R4: Afghan | S4: 🇦🇫 | T4: U+1F1E6 U+1F1EB
A5: 1 | B5: 2 | C5: Aland Islands | D5: ALA | E5: AX | F5: 248 | G5: 358 | H5: Mariehamn | I5: EUR | J5: Euro | K5: € | L5: .ax | M5: Åland | N5: Europe | O5: 4 | P5: Northern Europe | Q5: 18 | R5: Aland Island | S5: 🇦🇽 | T5: U+1F1E6 U+1F1FD
A6: 2 | B6: 3 | C6: Albania | D6: ALB | E6: AL | F6: 8 | G6: 355 | H6: Tirana | I6: ALL | J6: Albanian lek | K6: Lek | L6: .al | M6: Shqipëria | N6: Europe | O6: 4 | P6: Southern Europe | Q6: 16 | R6: Albanian | S6: 🇦🇱 | T6: U+1F1E6 U+1F1F1
A7: 3 | B7: 4 | C7: Algeria | D7: DZA | E7: DZ | F7: 12 | G7: 213 | H7: Algiers | I7: DZD | J7: Algerian dinar | K7: دج | L7: .dz | M7: الجزائر | N7: Africa | O7: 1 | P7: Northern Africa | Q7: 1 | R7: Algerian | S7: 🇩🇿 | T7: U+1F1E9 U+1F1FF
A8: 4 | B8: 5 | C8: American Samoa | D8: ASM | E8: AS | F8: 16 | G8: 1 | H8: Pago Pago | I8: USD | J8: United States dollar | K8: $ | L8: .as | M8: American Samoa | N8: Oceania | O8: 5 | P8: Polynesia | Q8: 22 | R8: American Samoan | S8: 🇦🇸 | T8: U+1F1E6 U+1F1F8
A9: 5 | B9: 6 | C9: Andorra | D9: AND | E9: AD | F9: 20 | G9: 376 | H9: Andorra la Vella | I9: EUR | J9: Euro | K9: € | L9: .ad | M9: Andorra | N9: Europe | O9: 4 | P9: Southern Europe | Q9: 16 | R9: Andorran | S9: 🇦🇩 | T9: U+1F1E6 U+1F1E9
A10: 6 | B10: 7 | C10: Angola | D10: AGO | E10: AO | F10: 24 | G10: 244 | H10: Luanda | I10: AOA | J10: Angolan kwanza | K10: Kz | L10: .ao | M10: Angola | N10: Africa | O10: 1 | P10: Middle Africa | Q10: 2 | R10: Angolan | S10: 🇦🇴 | T10: U+1F1E6 U+1F1F4
A11: 7 | B11: 8 | C11: Anguilla | D11: AIA | E11: AI | F11: 660 | G11: 1 | H11: The Valley | I11: XCD | J11: Eastern Caribbean dollar | K11: $ | L11: .ai | M11: Anguilla | N11: Americas | O11: 2 | P11: Caribbean | Q11: 7 | R11: Anguillan | S11: 🇦🇮 | T11: U+1F1E6 U+1F1EE
A12: 8 | B12: 9 | C12: Antarctica | D12: ATA | E12: AQ | F12: 10 | G12: 672 | I12: AAD | J12: Antarctican dollar | K12: $ | L12: .aq | M12: Antarctica | N12: Polar | O12: 6 | R12: Antarctic | S12: 🇦🇶 | T12: U+1F1E6 U+1F1F6
A13: 9 | B13: 10 | C13: Antigua and Barbuda | D13: ATG | E13: AG | F13: 28 | G13: 1 | H13: St. John's | I13: XCD | J13: Eastern Caribbean dollar | K13: $ | L13: .ag | M13: Antigua and Barbuda | N13: Americas | O13: 2 | P13: Caribbean | Q13: 7 | R13: Antiguan or Barbudan | S13: 🇦🇬 | T13: U+1F1E6 U+1F1EC
A14: 10 | B14: 11 | C14: Argentina | D14: ARG | E14: AR | F14: 32 | G14: 54 | H14: Buenos Aires | I14: ARS | J14: Argentine peso | K14: $ | L14: .ar | M14: Argentina | N14: Americas | O14: 2 | P14: South America | Q14: 8 | R14: Argentine | S14: 🇦🇷 | T14: U+1F1E6 U+1F1F7
A15: 11 | B15: 12 | C15: Armenia | D15: ARM | E15: AM | F15: 51 | G15: 374 | H15: Yerevan | I15: AMD | J15: Armenian dram | K15: ֏ | L15: .am | M15: Հայաստան | N15: Asia | O15: 3 | P15: Western Asia | Q15: 11 | R15: Armenian | S15: 🇦🇲 | T15: U+1F1E6 U+1F1F2
A16: 12 | B16: 13 | C16: Aruba | D16: ABW | E16: AW | F16: 533 | G16: 297 | H16: Oranjestad | I16: AWG | J16: Aruban florin | K16: ƒ | L16: .aw | M16: Aruba | N16: Americas | O16: 2 | P16: Caribbean | Q16: 7 | R16: Aruban | S16: 🇦🇼 | T16: U+1F1E6 U+1F1FC
A17: 13 | B17: 14 | C17: Australia | D17: AUS | E17: AU | F17: 36 | G17: 61 | H17: Canberra | I17: AUD | J17: Australian dollar | K17: $ | L17: .au | M17: Australia | N17: Oceania | O17: 5 | P17: Australia and New Zealand | Q17: 19 | R17: Australian | S17: 🇦🇺 | T17: U+1F1E6 U+1F1FA
A18: 14 | B18: 15 | C18: Austria | D18: AUT | E18: AT | F18: 40 | G18: 43 | H18: Vienna | I18: EUR | J18: Euro | K18: € | L18: .at | M18: Österreich | N18: Europe | O18: 4 | P18: Western Europe | Q18: 17 | R18: Austrian | S18: 🇦🇹 | T18: U+1F1E6 U+1F1F9
A19: 15 | B19: 16 | C19: Azerbaijan | D19: AZE | E19: AZ | F19: 31 | G19: 994 | H19: Baku | I19: AZN | J19: Azerbaijani manat | K19: m | L19: .az | M19: Azərbaycan | N19: Asia | O19: 3 | P19: Western Asia | Q19: 11 | R19: Azerbaijani, Azeri | S19: 🇦🇿 | T19: U+1F1E6 U+1F1FF
A20: 16 | B20: 17 | C20: Bahrain | D20: BHR | E20: BH | F20: 48 | G20: 973 | H20: Manama | I20: BHD | J20: Bahraini dinar | K20: .د.ب | L20: .bh | M20: ‏البحرين | N20: Asia | O20: 3 | P20: Western Asia | Q20: 11 | R20: Bahraini | S20: 🇧🇭 | T20: U+1F1E7 U+1F1ED
A21: 17 | B21: 18 | C21: Bangladesh | D21: BGD | E21: BD | F21: 50 | G21: 880 | H21: Dhaka | I21: BDT | J21: Bangladeshi taka | K21: ৳ | L21: .bd | M21: Bangladesh | N21: Asia | O21: 3 | P21: Southern Asia | Q21: 14 | R21: Bangladeshi | S21: 🇧🇩 | T21: U+1F1E7 U+1F1E9
A22: 18 | B22: 19 | C22: Barbados | D22: BRB | E22: BB | F22: 52 | G22: 1 | H22: Bridgetown | I22: BBD | J22: Barbadian dollar | K22: Bds$ | L22: .bb | M22: Barbados | N22: Americas | O22: 2 | P22: Caribbean | Q22: 7 | R22: Barbadian | S22: 🇧🇧 | T22: U+1F1E7 U+1F1E7
A23: 19 | B23: 20 | C23: Belarus | D23: BLR | E23: BY | F23: 112 | G23: 375 | H23: Minsk | I23: BYN | J23: Belarusian ruble | K23: Br | L23: .by | M23: Белару́сь | N23: Europe | O23: 4 | P23: Eastern Europe | Q23: 15 | R23: Belarusian | S23: 🇧🇾 | T23: U+1F1E7 U+1F1FE
A24: 20 | B24: 21 | C24: Belgium | D24: BEL | E24: BE | F24: 56 | G24: 32 | H24: Brussels | I24: EUR | J24: Euro | K24: € | L24: .be | M24: België | N24: Europe | O24: 4 | P24: Western Europe | Q24: 17 | R24: Belgian | S24: 🇧🇪 | T24: U+1F1E7 U+1F1EA
... A32: 28 | B32: 29 | C32: Botswana | D32: BWA | E32: BW | F32: 72 | G32: 267 | H32: Gaborone | I32: BWP | J32: Botswana pula | K32: P | L32: .bw | M32: Botswana | N32: Africa | O32: 1 | P32: Southern Africa | Q32: 5 | R32: Motswana, Botswanan | S32: 🇧🇼 | T32: U+1F1E7 U+1F1FC
A33: 29 | B33: 30 | C33: Bouvet Island | D33: BVT | E33: BV | F33: 74 | G33: 55 | I33: NOK | J33: Norwegian krone | K33: ko | L33: .bv | M33: Bouvetøya | R33: Bouvet Island | S33: 🇧🇻 | T33: U+1F1E7 U+1F1FB
A34: 30 | B34: 31 | C34: Brazil | D34: BRA | E34: BR | F34: 76 | G34: 55 | H34: Brasilia | I34: BRL | J34: Brazilian real | K34: R$ | L34: .br | M34: Brasil | N34: Americas | O34: 2 | P34: South America | Q34: 8 | R34: Brazilian | S34: 🇧🇷 | T34: U+1F1E7 U+1F1F7
A35: 31 | B35: 32 | C35: British Indian Ocean Territory | D35: IOT | E35: IO | F35: 86 | G35: 246 | H35: Diego Garcia | I35: USD | J35: United States dollar | K35: $ | L35: .io | M35: British Indian Ocean Territory | N35: Africa | O35: 1 | P35: Eastern Africa | Q35: 4 | R35: BIOT | S35: 🇮🇴 | T35: U+1F1EE U+1F1F4
A36: 32 | B36: 33 | C36: Brunei | D36: BRN | E36: BN | F36: 96 | G36: 673 | H36: Bandar Seri Begawan | I36: BND | J36: Brunei dollar | K36: B$ | L36: .bn | M36: Negara Brunei Darussalam | N36: Asia | O36: 3 | P36: South-Eastern Asia | Q36: 13 | R36: Bruneian | S36: 🇧🇳 | T36: U+1F1E7 U+1F1F3
A37: 33 | B37: 34 | C37: Bulgaria | D37: BGR | E37: BG | F37: 100 | G37: 359 | H37: Sofia | I37: BGN | J37: Bulgarian lev | K37: Лв. | L37: .bg | M37: България | N37: Europe | O37: 4 | P37: Eastern Europe | Q37: 15 | R37: Bulgarian | S37: 🇧🇬 | T37: U+1F1E7 U+1F1EC
A38: 34 | B38: 35 | C38: Burkina Faso | D38: BFA | E38: BF | F38: 854 | G38: 226 | H38: Ouagadougou | I38: XOF | J38: West African CFA franc | K38: CFA | L38: .bf | M38: Burkina Faso | N38: Africa | O38: 1 | P38: Western Africa | Q38: 3 | R38: Burkinabe | S38: 🇧🇫 | T38: U+1F1E7 U+1F1EB
A39: 35 | B39: 36 | C39: Burundi | D39: BDI | E39: BI | F39: 108 | G39: 257 | H39: Bujumbura | I39: BIF | J39: Burundian franc | K39: FBu | L39: .bi | M39: Burundi | N39: Africa | O39: 1 | P39: Eastern Africa | Q39: 4 | R39: Burundian | S39: 🇧🇮 | T39: U+1F1E7 U+1F1EE
A40: 36 | B40: 37 | C40: Cambodia | D40: KHM | E40: KH | F40: 116 | G40: 855 | H40: Phnom Penh | I40: KHR | J40: Cambodian riel | K40: KHR | L40: .kh | M40: Kâmpŭchéa | N40: Asia | O40: 3 | P40: South-Eastern Asia | Q40: 13 | R40: Cambodian | S40: 🇰🇭 | T40: U+1F1F0 U+1F1ED
A41: 37 | B41: 38 | C41: Cameroon | D41: CMR | E41: CM | F41: 120 | G41: 237 | H41: Yaounde | I41: XAF | J41: Central African CFA franc | K41: FCFA | L41: .cm | M41: Cameroon | N41: Africa | O41: 1 | P41: Middle Africa | Q41: 2 | R41: Cameroonian | S41: 🇨🇲 | T41: U+1F1E8 U+1F1F2
A42: 38 | B42: 39 | C42: Canada | D42: CAN | E42: CA | F42: 124 | G42: 1 | H42: Ottawa | I42: CAD | J42: Canadian dollar | K42: $ | L42: .ca | M42: Canada | N42: Americas | O42: 2 | P42: Northern America | Q42: 6 | R42: Canadian | S42: 🇨🇦 | T42: U+1F1E8 U+1F1E6
A43: 39 | B43: 40 | C43: Cape Verde | D43: CPV | E43: CV | F43: 132 | G43: 238 | H43: Praia | I43: CVE | J43: Cape Verdean escudo | K43: $ | L43: .cv | M43: Cabo Verde | N43: Africa | O43: 1 | P43: Western Africa | Q43: 3 | R43: Verdean | S43: 🇨🇻 | T43: U+1F1E8 U+1F1FB
A44: 40 | B44: 41 | C44: Cayman Islands | D44: CYM | E44: KY | F44: 136 | G44: 1 | H44: George Town | I44: KYD | J44: Cayman Islands dollar | K44: $ | L44: .ky | M44: Cayman Islands | N44: Americas | O44: 2 | P44: Caribbean | Q44: 7 | R44: Caymanian | S44: 🇰🇾 | T44: U+1F1F0 U+1F1FE
A45: 41 | B45: 42 | C45: Central African Republic | D45: CAF | E45: CF | F45: 140 | G45: 236 | H45: Bangui | I45: XAF | J45: Central African CFA franc | K45: FCFA | L45: .cf | M45: Ködörösêse tî Bêafrîka | N45: Africa | O45: 1 | P45: Middle Africa | Q45: 2 | R45: Central African | S45: 🇨🇫 | T45: U+1F1E8 U+1F1EB
... A55: 51 | B55: 52 | C55: Costa Rica | D55: CRI | E55: CR | F55: 188 | G55: 506 | H55: San Jose | I55: CRC | J55: Costa Rican colón | K55: ₡ | L55: .cr | M55: Costa Rica | N55: Americas | O55: 2 | P55: Central America | Q55: 9 | R55: Costa Rican | S55: 🇨🇷 | T55: U+1F1E8 U+1F1F7
A56: 52 | B56: 53 | C56: Cote D'Ivoire (Ivory Coast) | D56: CIV | E56: CI | F56: 384 | G56: 225 | H56: Yamoussoukro | I56: XOF | J56: West African CFA franc | K56: CFA | L56: .ci | N56: Africa | O56: 1 | P56: Western Africa | Q56: 3 | R56: Ivorian | S56: 🇨🇮 | T56: U+1F1E8 U+1F1EE
A57: 53 | B57: 54 | C57: Croatia | D57: HRV | E57: HR | F57: 191 | G57: 385 | H57: Zagreb | I57: EUR | J57: Euro | K57: € | L57: .hr | M57: Hrvatska | N57: Europe | O57: 4 | P57: Southern Europe | Q57: 16 | R57: Croatian | S57: 🇭🇷 | T57: U+1F1ED U+1F1F7
A58: 54 | B58: 55 | C58: Cuba | D58: CUB | E58: CU | F58: 192 | G58: 53 | H58: Havana | I58: CUP | J58: Cuban peso | K58: $ | L58: .cu | M58: Cuba | N58: Americas | O58: 2 | P58: Caribbean | Q58: 7 | R58: Cuban | S58: 🇨🇺 | T58: U+1F1E8 U+1F1FA
A59: 55 | B59: 56 | C59: Curaçao | D59: CUW | E59: CW | F59: 531 | G59: 599 | H59: Willemstad | I59: ANG | J59: Netherlands Antillean guilder | K59: ƒ | L59: .cw | M59: Curaçao | N59: Americas | O59: 2 | P59: Caribbean | Q59: 7 | R59: Curacaoan | S59: 🇨🇼 | T59: U+1F1E8 U+1F1FC
A60: 56 | B60: 57 | C60: Cyprus | D60: CYP | E60: CY | F60: 196 | G60: 357 | H60: Nicosia | I60: EUR | J60: Euro | K60: € | L60: .cy | M60: Κύπρος | N60: Europe | O60: 4 | P60: Southern Europe | Q60: 16 | R60: Cypriot | S60: 🇨🇾 | T60: U+1F1E8 U+1F1FE
A61: 57 | B61: 58 | C61: Czech Republic | D61: CZE | E61: CZ | F61: 203 | G61: 420 | H61: Prague | I61: CZK | J61: Czech koruna | K61: Kč | L61: .cz | M61: Česká republika | N61: Europe | O61: 4 | P61: Eastern Europe | Q61: 15 | R61: Czech | S61: 🇨🇿 | T61: U+1F1E8 U+1F1FF
A62: 58 | B62: 59 | C62: Democratic Republic of the Congo | D62: COD | E62: CD | F62: 180 | G62: 243 | H62: Kinshasa | I62: CDF | J62: Congolese Franc | K62: FC | L62: .cd | M62: République démocratique du Congo | N62: Africa | O62: 1 | P62: Middle Africa | Q62: 2 | R62: Congolese | S62: 🇨🇩 | T62: U+1F1E8 U+1F1E9
A63: 59 | B63: 60 | C63: Denmark | D63: DNK | E63: DK | F63: 208 | G63: 45 | H63: Copenhagen | I63: DKK | J63: Danish krone | K63: Kr. | L63: .dk | M63: Danmark | N63: Europe | O63: 4 | P63: Northern Europe | Q63: 18 | R63: Danish | S63: 🇩🇰 | T63: U+1F1E9 U+1F1F0
A64: 60 | B64: 61 | C64: Djibouti | D64: DJI | E64: DJ | F64: 262 | G64: 253 | H64: Djibouti | I64: DJF | J64: Djiboutian franc | K64: Fdj | L64: .dj | M64: Djibouti | N64: Africa | O64: 1 | P64: Eastern Africa | Q64: 4 | R64: Djiboutian | S64: 🇩🇯 | T64: U+1F1E9 U+1F1EF
A65: 61 | B65: 62 | C65: Dominica | D65: DMA | E65: DM | F65: 212 | G65: 1 | H65: Roseau | I65: XCD | J65: Eastern Caribbean dollar | K65: $ | L65: .dm | M65: Dominica | N65: Americas | O65: 2 | P65: Caribbean | Q65: 7 | R65: Dominican | S65: 🇩🇲 | T65: U+1F1E9 U+1F1F2
A66: 62 | B66: 63 | C66: Dominican Republic | D66: DOM | E66: DO | F66: 214 | G66: 1 | H66: Santo Domingo | I66: DOP | J66: Dominican peso | K66: $ | L66: .do | M66: República Dominicana | N66: Americas | O66: 2 | P66: Caribbean | Q66: 7 | R66: Dominican | S66: 🇩🇴 | T66: U+1F1E9 U+1F1F4
A67: 63 | B67: 64 | C67: Ecuador | D67: ECU | E67: EC | F67: 218 | G67: 593 | H67: Quito | I67: USD | J67: United States dollar | K67: $ | L67: .ec | M67: Ecuador | N67: Americas | O67: 2 | P67: South America | Q67: 8 | R67: Ecuadorian | S67: 🇪🇨 | T67: U+1F1EA U+1F1E8
A68: 64 | B68: 65 | C68: Egypt | D68: EGY | E68: EG | F68: 818 | G68: 20 | H68: Cairo | I68: EGP | J68: Egyptian pound | K68: ج.م | L68: .eg | M68: مصر‎ | N68: Africa | O68: 1 | P68: Northern Africa | Q68: 1 | R68: Egyptian | S68: 🇪🇬 | T68: U+1F1EA U+1F1EC
... A98: 94 | B98: 95 | C98: Haiti | D98: HTI | E98: HT | F98: 332 | G98: 509 | H98: Port-au-Prince | I98: HTG | J98: Haitian gourde | K98: G | L98: .ht | M98: Haïti | N98: Americas | O98: 2 | P98: Caribbean | Q98: 7 | R98: Haitian | S98: 🇭🇹 | T98: U+1F1ED U+1F1F9
A99: 95 | B99: 96 | C99: Heard Island and McDonald Islands | D99: HMD | E99: HM | F99: 334 | G99: 672 | I99: AUD | J99: Australian dollar | K99: $ | L99: .hm | M99: Heard Island and McDonald Islands | R99: Heard Island or McDonald Islands | S99: 🇭🇲 | T99: U+1F1ED U+1F1F2
A100: 96 | B100: 97 | C100: Honduras | D100: HND | E100: HN | F100: 340 | G100: 504 | H100: Tegucigalpa | I100: HNL | J100: Honduran lempira | K100: L | L100: .hn | M100: Honduras | N100: Americas | O100: 2 | P100: Central America | Q100: 9 | R100: Honduran | S100: 🇭🇳 | T100: U+1F1ED U+1F1F3
A101: 97 | B101: 98 | C101: Hong Kong S.A.R. | D101: HKG | E101: HK | F101: 344 | G101: 852 | H101: Hong Kong | I101: HKD | J101: Hong Kong dollar | K101: $ | L101: .hk | M101: 香港 | N101: Asia | O101: 3 | P101: Eastern Asia | Q101: 12 | R101: Hong Kong, Hong Kongese | S101: 🇭🇰 | T101: U+1F1ED U+1F1F0
A102: 98 | B102: 99 | C102: Hungary | D102: HUN | E102: HU | F102: 348 | G102: 36 | H102: Budapest | I102: HUF | J102: Hungarian forint | K102: Ft | L102: .hu | M102: Magyarország | N102: Europe | O102: 4 | P102: Eastern Europe | Q102: 15 | R102: Hungarian, Magyar | S102: 🇭🇺 | T102: U+1F1ED U+1F1FA
A103: 99 | B103: 100 | C103: Iceland | D103: ISL | E103: IS | F103: 352 | G103: 354 | H103: Reykjavik | I103: ISK | J103: Icelandic króna | K103: ko | L103: .is | M103: Ísland | N103: Europe | O103: 4 | P103: Northern Europe | Q103: 18 | R103: Icelandic | S103: 🇮🇸 | T103: U+1F1EE U+1F1F8
A104: 100 | B104: 101 | C104: India | D104: IND | E104: IN | F104: 356 | G104: 91 | H104: New Delhi | I104: INR | J104: Indian rupee | K104: ₹ | L104: .in | M104: भारत | N104: Asia | O104: 3 | P104: Southern Asia | Q104: 14 | R104: Indian | S104: 🇮🇳 | T104: U+1F1EE U+1F1F3
A105: 101 | B105: 102 | C105: Indonesia | D105: IDN | E105: ID | F105: 360 | G105: 62 | H105: Jakarta | I105: IDR | J105: Indonesian rupiah | K105: Rp | L105: .id | M105: Indonesia | N105: Asia | O105: 3 | P105: South-Eastern Asia | Q105: 13 | R105: Indonesian | S105: 🇮🇩 | T105: U+1F1EE U+1F1E9
A106: 102 | B106: 103 | C106: Iran | D106: IRN | E106: IR | F106: 364 | G106: 98 | H106: Tehran | I106: IRR | J106: Iranian rial | K106: ﷼ | L106: .ir | M106: ایران | N106: Asia | O106: 3 | P106: Southern Asia | Q106: 14 | R106: Iranian, Persian | S106: 🇮🇷 | T106: U+1F1EE U+1F1F7
A107: 103 | B107: 104 | C107: Iraq | D107: IRQ | E107: IQ | F107: 368 | G107: 964 | H107: Baghdad | I107: IQD | J107: Iraqi dinar | K107: د.ع | L107: .iq | M107: العراق | N107: Asia | O107: 3 | P107: Western Asia | Q107: 11 | R107: Iraqi | S107: 🇮🇶 | T107: U+1F1EE U+1F1F6
A108: 104 | B108: 105 | C108: Ireland | D108: IRL | E108: IE | F108: 372 | G108: 353 | H108: Dublin | I108: EUR | J108: Euro | K108: € | L108: .ie | M108: Éire | N108: Europe | O108: 4 | P108: Northern Europe | Q108: 18 | R108: Irish | S108: 🇮🇪 | T108: U+1F1EE U+1F1EA
A109: 105 | B109: 106 | C109: Israel | D109: ISR | E109: IL | F109: 376 | G109: 972 | H109: Jerusalem | I109: ILS | J109: Israeli new shekel | K109: ₪ | L109: .il | M109: יִשְׂרָאֵל | N109: Asia | O109: 3 | P109: Western Asia | Q109: 11 | R109: Israeli | S109: 🇮🇱 | T109: U+1F1EE U+1F1F1
A110: 106 | B110: 107 | C110: Italy | D110: ITA | E110: IT | F110: 380 | G110: 39 | H110: Rome | I110: EUR | J110: Euro | K110: € | L110: .it | M110: Italia | N110: Europe | O110: 4 | P110: Southern Europe | Q110: 16 | R110: Italian | S110: 🇮🇹 | T110: U+1F1EE U+1F1F9
A111: 107 | B111: 108 | C111: Jamaica | D111: JAM | E111: JM | F111: 388 | G111: 1 | H111: Kingston | I111: JMD | J111: Jamaican dollar | K111: J$ | L111: .jm | M111: Jamaica | N111: Americas | O111: 2 | P111: Caribbean | Q111: 7 | R111: Jamaican | S111: 🇯🇲 | T111: U+1F1EF U+1F1F2
... A226: 222 | B226: 223 | C226: Togo | D226: TGO | E226: TG | F226: 768 | G226: 228 | H226: Lome | I226: XOF | J226: West African CFA franc | K226: CFA | L226: .tg | M226: Togo | N226: Africa | O226: 1 | P226: Western Africa | Q226: 3 | R226: Togolese | S226: 🇹🇬 | T226: U+1F1F9 U+1F1EC
A227: 223 | B227: 224 | C227: Tokelau | D227: TKL | E227: TK | F227: 772 | G227: 690 | I227: NZD | J227: New Zealand dollar | K227: $ | L227: .tk | M227: Tokelau | N227: Oceania | O227: 5 | P227: Polynesia | Q227: 22 | R227: Tokelauan | S227: 🇹🇰 | T227: U+1F1F9 U+1F1F0
A228: 224 | B228: 225 | C228: Tonga | D228: TON | E228: TO | F228: 776 | G228: 676 | H228: Nuku'alofa | I228: TOP | J228: Tongan paʻanga | K228: $ | L228: .to | M228: Tonga | N228: Oceania | O228: 5 | P228: Polynesia | Q228: 22 | R228: Tongan | S228: 🇹🇴 | T228: U+1F1F9 U+1F1F4
A229: 225 | B229: 226 | C229: Trinidad and Tobago | D229: TTO | E229: TT | F229: 780 | G229: 1 | H229: Port of Spain | I229: TTD | J229: Trinidad and Tobago dollar | K229: $ | L229: .tt | M229: Trinidad and Tobago | N229: Americas | O229: 2 | P229: Caribbean | Q229: 7 | R229: Trinidadian or Tobagonian | S229: 🇹🇹 | T229: U+1F1F9 U+1F1F9
A230: 226 | B230: 227 | C230: Tunisia | D230: TUN | E230: TN | F230: 788 | G230: 216 | H230: Tunis | I230: TND | J230: Tunisian dinar | K230: ت.د | L230: .tn | M230: تونس | N230: Africa | O230: 1 | P230: Northern Africa | Q230: 1 | R230: Tunisian | S230: 🇹🇳 | T230: U+1F1F9 U+1F1F3
A231: 227 | B231: 228 | C231: Türkiye | D231: TUR | E231: TR | F231: 792 | G231: 90 | H231: Ankara | I231: TRY | J231: Turkish lira | K231: ₺ | L231: .tr | M231: Türkiye | N231: Asia | O231: 3 | P231: Western Asia | Q231: 11 | R231: Turkish | S231: 🇹🇷 | T231: U+1F1F9 U+1F1F7
A232: 228 | B232: 229 | C232: Turkmenistan | D232: TKM | E232: TM | F232: 795 | G232: 993 | H232: Ashgabat | I232: TMT | J232: Turkmenistan manat | K232: T | L232: .tm | M232: Türkmenistan | N232: Asia | O232: 3 | P232: Central Asia | Q232: 10 | R232: Turkmen | S232: 🇹🇲 | T232: U+1F1F9 U+1F1F2
A233: 229 | B233: 230 | C233: Turks and Caicos Islands | D233: TCA | E233: TC | F233: 796 | G233: 1 | H233: Cockburn Town | I233: USD | J233: United States dollar | K233: $ | L233: .tc | M233: Turks and Caicos Islands | N233: Americas | O233: 2 | P233: Caribbean | Q233: 7 | R233: Turks and Caicos Island | S233: 🇹🇨 | T233: U+1F1F9 U+1F1E8
A234: 230 | B234: 231 | C234: Tuvalu | D234: TUV | E234: TV | F234: 798 | G234: 688 | H234: Funafuti | I234: AUD | J234: Australian dollar | K234: $ | L234: .tv | M234: Tuvalu | N234: Oceania | O234: 5 | P234: Polynesia | Q234: 22 | R234: Tuvaluan | S234: 🇹🇻 | T234: U+1F1F9 U+1F1FB
A235: 231 | B235: 232 | C235: Uganda | D235: UGA | E235: UG | F235: 800 | G235: 256 | H235: Kampala | I235: UGX | J235: Ugandan shilling | K235: USh | L235: .ug | M235: Uganda | N235: Africa | O235: 1 | P235: Eastern Africa | Q235: 4 | R235: Ugandan | S235: 🇺🇬 | T235: U+1F1FA U+1F1EC
A236: 232 | B236: 233 | C236: Ukraine | D236: UKR | E236: UA | F236: 804 | G236: 380 | H236: Kyiv | I236: UAH | J236: Ukrainian hryvnia | K236: ₴ | L236: .ua | M236: Україна | N236: Europe | O236: 4 | P236: Eastern Europe | Q236: 15 | R236: Ukrainian | S236: 🇺🇦 | T236: U+1F1FA U+1F1E6
A237: 233 | B237: 234 | C237: United Arab Emirates | D237: ARE | E237: AE | F237: 784 | G237: 971 | H237: Abu Dhabi | I237: AED | J237: United Arab Emirates dirham | K237: إ.د | L237: .ae | M237: دولة الإمارات العربية المتحدة | N237: Asia | O237: 3 | P237: Western Asia | Q237: 11 | R237: Emirati, Emirian, Emiri | S237: 🇦🇪 | T237: U+1F1E6 U+1F1EA
A238: 234 | B238: 235 | C238: United Kingdom | D238: GBR | E238: GB | F238: 826 | G238: 44 | H238: London | I238: GBP | J238: British pound | K238: £ | L238: .uk | M238: United Kingdom | N238: Europe | O238: 4 | P238: Northern Europe | Q238: 18 | R238: British, UK | S238: 🇬🇧 | T238: U+1F1EC U+1F1E7
A239: 235 | B239: 236 | C239: United States | D239: USA | E239: US | F239: 840 | G239: 1 | H239: Washington | I239: USD | J239: United States dollar | K239: $ | L239: .us | M239: United States | N239: Americas | O239: 2 | P239: Northern America | Q239: 6 | R239: American | S239: 🇺🇸 | T239: U+1F1FA U+1F1F8
A240: 236 | B240: 237 | C240: United States Minor Outlying Islands | D240: UMI | E240: UM | F240: 581 | G240: 1 | I240: USD | J240: United States dollar | K240: $ | L240: .us | M240: United States Minor Outlying Islands | N240: Americas | O240: 2 | P240: Northern America | Q240: 6 | R240: American | S240: 🇺🇲 | T240: U+1F1FA U+1F1F2
A241: 237 | B241: 238 | C241: Uruguay | D241: URY | E241: UY | F241: 858 | G241: 598 | H241: Montevideo | I241: UYU | J241: Uruguayan peso | K241: $ | L241: .uy | M241: Uruguay | N241: Americas | O241: 2 | P241: South America | Q241: 8 | R241: Uruguayan | S241: 🇺🇾 | T241: U+1F1FA U+1F1FE
A242: 238 | B242: 239 | C242: Uzbekistan | D242: UZB | E242: UZ | F242: 860 | G242: 998 | H242: Tashkent | I242: UZS | J242: Uzbekistani soʻm | K242: лв | L242: .uz | M242: O‘zbekiston | N242: Asia | O242: 3 | P242: Central Asia | Q242: 10 | R242: Uzbekistani, Uzbek | S242: 🇺🇿 | T242: U+1F1FA U+1F1FF
A243: 239 | B243: 240 | C243: Vanuatu | D243: VUT | E243: VU | F243: 548 | G243: 678 | H243: Port Vila | I243: VUV | J243: Vanuatu vatu | K243: VT | L243: .vu | M243: Vanuatu | N243: Oceania | O243: 5 | P243: Melanesia | Q243: 20 | R243: Ni-Vanuatu, Vanuatuan | S243: 🇻🇺 | T243: U+1F1FB U+1F1FA
A244: 240 | B244: 241 | C244: Vatican City State (Holy See) | D244: VAT | E244: VA | F244: 336 | G244: 379 | H244: Vatican City | I244: EUR | J244: Euro | K244: € | L244: .va | M244: Vaticano | N244: Europe | O244: 4 | P244: Southern Europe | Q244: 16 | R244: Vatican | S244: 🇻🇦 | T244: U+1F1FB U+1F1E6
A245: 241 | B245: 242 | C245: Venezuela | D245: VEN | E245: VE | F245: 862 | G245: 58 | H245: Caracas | I245: VES | J245: Bolívar | K245: Bs | L245: .ve | M245: Venezuela | N245: Americas | O245: 2 | P245: South America | Q245: 8 | R245: Venezuelan | S245: 🇻🇪 | T245: U+1F1FB U+1F1EA
A246: 242 | B246: 243 | C246: Vietnam | D246: VNM | E246: VN | F246: 704 | G246: 84 | H246: Hanoi | I246: VND | J246: Vietnamese đồng | K246: ₫ | L246: .vn | M246: Việt Nam | N246: Asia | O246: 3 | P246: South-Eastern Asia | Q246: 13 | R246: Vietnamese | S246: 🇻🇳 | T246: U+1F1FB U+1F1F3
A247: 243 | B247: 244 | C247: Virgin Islands (British) | D247: VGB | E247: VG | F247: 92 | G247: 1 | H247: Road Town | I247: USD | J247: United States dollar | K247: $ | L247: .vg | M247: British Virgin Islands | N247: Americas | O247: 2 | P247: Caribbean | Q247: 7 | R247: British Virgin Island | S247: 🇻🇬 | T247: U+1F1FB U+1F1EC
A248: 244 | B248: 245 | C248: Virgin Islands (US) | D248: VIR | E248: VI | F248: 850 | G248: 1 | H248: Charlotte Amalie | I248: USD | J248: United States dollar | K248: $ | L248: .vi | M248: United States Virgin Islands | N248: Americas | O248: 2 | P248: Caribbean | Q248: 7 | R248: U.S. Virgin Island | S248: 🇻🇮 | T248: U+1F1FB U+1F1EE
A249: 245 | B249: 246 | C249: Wallis and Futuna Islands | D249: WLF | E249: WF | F249: 876 | G249: 681 | H249: Mata Utu | I249: XPF | J249: CFP franc | K249: ₣ | L249: .wf | M249: Wallis et Futuna | N249: Oceania | O249: 5 | P249: Polynesia | Q249: 22 | R249: Wallis and Futuna, Wallisian or Futunan | S249: 🇼🇫 | T249: U+1F1FC U+1F1EB
A250: 246 | B250: 247 | C250: Western Sahara | D250: ESH | E250: EH | F250: 732 | G250: 212 | H250: El-Aaiun | I250: MAD | J250: Moroccan dirham | K250: MAD | L250: .eh | M250: الصحراء الغربية | N250: Africa | O250: 1 | P250: Northern Africa | Q250: 1 | R250: Sahrawi, Sahrawian, Sahraouian | S250: 🇪🇭 | T250: U+1F1EA U+1F1ED
A251: 247 | B251: 248 | C251: Yemen | D251: YEM | E251: YE | F251: 887 | G251: 967 | H251: Sanaa | I251: YER | J251: Yemeni rial | K251: ﷼ | L251: .ye | M251: اليَمَن | N251: Asia | O251: 3 | P251: Western Asia | Q251: 11 | R251: Yemeni | S251: 🇾🇪 | T251: U+1F1FE U+1F1EA
A252: 248 | B252: 249 | C252: Zambia | D252: ZMB | E252: ZM | F252: 894 | G252: 260 | H252: Lusaka | I252: ZMW | J252: Zambian kwacha | K252: ZK | L252: .zm | M252: Zambia | N252: Africa | O252: 1 | P252: Southern Africa | Q252: 5 | R252: Zambian | S252: 🇿🇲 | T252: U+1F1FF U+1F1F2
A253: 249 | B253: 250 | C253: Zimbabwe | D253: ZWE | E253: ZW | F253: 716 | G253: 263 | H253: Harare | I253: ZWL | J253: Zimbabwe Dollar | K253: $ | L253: .zw | M253: Zimbabwe | N253: Africa | O253: 1 | P253: Eastern Africa | Q253: 4 | R253: Zimbabwean | S253: 🇿🇼 | T253: U+1F1FF U+1F1FC
A254: End IDs of object [dbo.countries] on sheet [countries]
A255: Start IDs of object [dbo.studios] on sheet [studios]
A256: _RowNum | B256: studio_ID
A257: 0 | B257: 2
A258: 1 | B258: 3
A259: 2 | B259: 4
...

Sheet SaveToDB_UpdatedID
A1: ID
A2: Start IDs of object [dbo.studios] on sheet [studios]
A3: 194
A4: End IDs of object [dbo.studios] on sheet [studios]

Sheet SaveToDB_Lists
A1: ID
